{
"meta":{"test_sets":[],"test_metrics":[],"learn_metrics":[{"best_value":"Min","name":"RMSE"}],"launch_mode":"Train","parameters":"","iteration_count":950,"learn_sets":["learn"],"name":"experiment"},
"iterations":[
{"learn":[0.3886781669],"iteration":0,"passed_time":0.1501982547,"remaining_time":142.5381437},
{"learn":[0.3767528661],"iteration":1,"passed_time":0.1510240618,"remaining_time":71.58540528},
{"learn":[0.3653459825],"iteration":2,"passed_time":0.1518023261,"remaining_time":47.91893427},
{"learn":[0.3540950727],"iteration":3,"passed_time":0.1525278787,"remaining_time":36.07284331},
{"learn":[0.3439085597],"iteration":4,"passed_time":0.1532906361,"remaining_time":28.97193021},
{"learn":[0.3352556783],"iteration":5,"passed_time":0.1540103585,"remaining_time":24.23096307},
{"learn":[0.3268241884],"iteration":6,"passed_time":0.1547400684,"remaining_time":20.84569778},
{"learn":[0.3176637182],"iteration":7,"passed_time":0.1554705596,"remaining_time":18.30665839},
{"learn":[0.3086405041],"iteration":8,"passed_time":0.1562037955,"remaining_time":16.33197462},
{"learn":[0.3017019605],"iteration":9,"passed_time":0.1569085019,"remaining_time":14.74939917},
{"learn":[0.2934706894],"iteration":10,"passed_time":0.157615392,"remaining_time":13.45462301},
{"learn":[0.2866356222],"iteration":11,"passed_time":0.1583171231,"remaining_time":12.37512179},
{"learn":[0.2813619189],"iteration":12,"passed_time":0.1590735495,"remaining_time":11.46553199},
{"learn":[0.274948573],"iteration":13,"passed_time":0.159913992,"remaining_time":10.69139261},
{"learn":[0.269789311],"iteration":14,"passed_time":0.1606703382,"remaining_time":10.01511775},
{"learn":[0.2639671968],"iteration":15,"passed_time":0.1613880171,"remaining_time":9.421025498},
{"learn":[0.2587270931],"iteration":16,"passed_time":0.1621184782,"remaining_time":8.897443542},
{"learn":[0.2534714521],"iteration":17,"passed_time":0.1628515139,"remaining_time":8.432089496},
{"learn":[0.2486580442],"iteration":18,"passed_time":0.1635966506,"remaining_time":8.016235878},
{"learn":[0.244189638],"iteration":19,"passed_time":0.1643147402,"remaining_time":7.640635418},
{"learn":[0.2400636549],"iteration":20,"passed_time":0.1650158703,"remaining_time":7.299987785},
{"learn":[0.2357410794],"iteration":21,"passed_time":0.1656962743,"remaining_time":6.989370117},
{"learn":[0.2318064024],"iteration":22,"passed_time":0.1664012611,"remaining_time":6.706694308},
{"learn":[0.2283162013],"iteration":23,"passed_time":0.1670916926,"remaining_time":6.446954474},
{"learn":[0.223550479],"iteration":24,"passed_time":0.1678209617,"remaining_time":6.209375583},
{"learn":[0.2203581808],"iteration":25,"passed_time":0.1685455126,"remaining_time":5.989848216},
{"learn":[0.2161962606],"iteration":26,"passed_time":0.1692556984,"remaining_time":5.786037394},
{"learn":[0.2129766684],"iteration":27,"passed_time":0.1699464204,"remaining_time":5.596092844},
{"learn":[0.2107321353],"iteration":28,"passed_time":0.1706555044,"remaining_time":5.419783432},
{"learn":[0.2072104609],"iteration":29,"passed_time":0.1713751166,"remaining_time":5.255503577},
{"learn":[0.2039032741],"iteration":30,"passed_time":0.1720871056,"remaining_time":5.101550003},
{"learn":[0.2016516766],"iteration":31,"passed_time":0.1727732497,"remaining_time":4.9564326},
{"learn":[0.1987778992],"iteration":32,"passed_time":0.1734707835,"remaining_time":4.820385105},
{"learn":[0.1970373578],"iteration":33,"passed_time":0.174168117,"remaining_time":4.692293976},
{"learn":[0.1953384072],"iteration":34,"passed_time":0.1748902837,"remaining_time":4.572131703},
{"learn":[0.1931529047],"iteration":35,"passed_time":0.1755850427,"remaining_time":4.457909141},
{"learn":[0.1908625607],"iteration":36,"passed_time":0.1762628723,"remaining_time":4.34940547},
{"learn":[0.188925847],"iteration":37,"passed_time":0.1769364545,"remaining_time":4.246474907},
{"learn":[0.1868626284],"iteration":38,"passed_time":0.1776978194,"remaining_time":4.150838807},
{"learn":[0.1850663095],"iteration":39,"passed_time":0.1784260066,"remaining_time":4.05919165},
{"learn":[0.1836267882],"iteration":40,"passed_time":0.1791391776,"remaining_time":3.971646646},
{"learn":[0.1819271139],"iteration":41,"passed_time":0.1798787346,"remaining_time":3.888806929},
{"learn":[0.180282431],"iteration":42,"passed_time":0.1805902127,"remaining_time":3.809193557},
{"learn":[0.1788061445],"iteration":43,"passed_time":0.1813014705,"remaining_time":3.733162096},
{"learn":[0.1771088845],"iteration":44,"passed_time":0.1820262617,"remaining_time":3.660750375},
{"learn":[0.1759487234],"iteration":45,"passed_time":0.1827282333,"remaining_time":3.59100702},
{"learn":[0.1745810277],"iteration":46,"passed_time":0.1834516923,"remaining_time":3.524614428},
{"learn":[0.1734639222],"iteration":47,"passed_time":0.1841650436,"remaining_time":3.460768112},
{"learn":[0.1716174768],"iteration":48,"passed_time":0.1848871002,"remaining_time":3.399658719},
{"learn":[0.1702434661],"iteration":49,"passed_time":0.1855868278,"remaining_time":3.340562901},
{"learn":[0.1688276982],"iteration":50,"passed_time":0.1862951705,"remaining_time":3.283908986},
{"learn":[0.1679111678],"iteration":51,"passed_time":0.1870314017,"remaining_time":3.229888436},
{"learn":[0.1665926714],"iteration":52,"passed_time":0.1877394638,"remaining_time":3.177401869},
{"learn":[0.1652588642],"iteration":53,"passed_time":0.1884365469,"remaining_time":3.126650852},
{"learn":[0.1643208837],"iteration":54,"passed_time":0.1891505694,"remaining_time":3.07799563},
{"learn":[0.1633471991],"iteration":55,"passed_time":0.1898440963,"remaining_time":3.030725395},
{"learn":[0.1620611223],"iteration":56,"passed_time":0.1905888022,"remaining_time":2.985891235},
{"learn":[0.1612262663],"iteration":57,"passed_time":0.1912766392,"remaining_time":2.941702796},
{"learn":[0.1602730678],"iteration":58,"passed_time":0.1919751548,"remaining_time":2.899150219},
{"learn":[0.1597115947],"iteration":59,"passed_time":0.1926714364,"remaining_time":2.857959641},
{"learn":[0.1587418525],"iteration":60,"passed_time":0.1934311986,"remaining_time":2.819021894},
{"learn":[0.1578381937],"iteration":61,"passed_time":0.1941313169,"remaining_time":2.780461442},
{"learn":[0.1571989156],"iteration":62,"passed_time":0.1948325873,"remaining_time":2.743119126},
{"learn":[0.1561688611],"iteration":63,"passed_time":0.1955253428,"remaining_time":2.706803964},
{"learn":[0.1556753161],"iteration":64,"passed_time":0.1962254912,"remaining_time":2.671685534},
{"learn":[0.1551949779],"iteration":65,"passed_time":0.1969071775,"remaining_time":2.637362801},
{"learn":[0.1541832063],"iteration":66,"passed_time":0.1976182649,"remaining_time":2.60443176},
{"learn":[0.1535589448],"iteration":67,"passed_time":0.1983384582,"remaining_time":2.572566472},
{"learn":[0.1531335047],"iteration":68,"passed_time":0.1991326502,"remaining_time":2.542548766},
{"learn":[0.1524790227],"iteration":69,"passed_time":0.1998445591,"remaining_time":2.5123316},
{"learn":[0.1518352806],"iteration":70,"passed_time":0.2006157812,"remaining_time":2.483679882},
{"learn":[0.1512960748],"iteration":71,"passed_time":0.2013660368,"remaining_time":2.455546948},
{"learn":[0.1507377717],"iteration":72,"passed_time":0.2021009256,"remaining_time":2.427979613},
{"learn":[0.150200976],"iteration":73,"passed_time":0.2028115422,"remaining_time":2.400850149},
{"learn":[0.1494424947],"iteration":74,"passed_time":0.2035098374,"remaining_time":2.374281436},
{"learn":[0.148896285],"iteration":75,"passed_time":0.2042382951,"remaining_time":2.348740393},
{"learn":[0.1483632954],"iteration":76,"passed_time":0.204952558,"remaining_time":2.323682898},
{"learn":[0.1477987109],"iteration":77,"passed_time":0.2056379608,"remaining_time":2.298926946},
{"learn":[0.1470340733],"iteration":78,"passed_time":0.2063458426,"remaining_time":2.275028214},
{"learn":[0.146676605],"iteration":79,"passed_time":0.2070513403,"remaining_time":2.251683326},
{"learn":[0.146205296],"iteration":80,"passed_time":0.2077693498,"remaining_time":2.229031666},
{"learn":[0.145727106],"iteration":81,"passed_time":0.2084597312,"remaining_time":2.206622521},
{"learn":[0.145273486],"iteration":82,"passed_time":0.2091439719,"remaining_time":2.184672574},
{"learn":[0.144874246],"iteration":83,"passed_time":0.2098624121,"remaining_time":2.163581535},
{"learn":[0.1443704711],"iteration":84,"passed_time":0.2105739103,"remaining_time":2.142899205},
{"learn":[0.1439675501],"iteration":85,"passed_time":0.2112866005,"remaining_time":2.122693289},
{"learn":[0.1436880849],"iteration":86,"passed_time":0.2120242442,"remaining_time":2.10318302},
{"learn":[0.1432937197],"iteration":87,"passed_time":0.2127448682,"remaining_time":2.083932686},
{"learn":[0.1428858953],"iteration":88,"passed_time":0.213495805,"remaining_time":2.065392001},
{"learn":[0.1422768012],"iteration":89,"passed_time":0.2141978166,"remaining_time":2.046779136},
{"learn":[0.1419056465],"iteration":90,"passed_time":0.2149162869,"remaining_time":2.02871528},
{"learn":[0.1416048327],"iteration":91,"passed_time":0.215611116,"remaining_time":2.010808017},
{"learn":[0.1410992445],"iteration":92,"passed_time":0.2163094913,"remaining_time":1.993303592},
{"learn":[0.1406408755],"iteration":93,"passed_time":0.2169883627,"remaining_time":1.975979133},
{"learn":[0.1401897801],"iteration":94,"passed_time":0.2176724131,"remaining_time":1.959051718},
{"learn":[0.139844069],"iteration":95,"passed_time":0.2183616926,"remaining_time":1.942509224},
{"learn":[0.1396190531],"iteration":96,"passed_time":0.2190467547,"remaining_time":1.926256513},
{"learn":[0.1393813439],"iteration":97,"passed_time":0.2197291723,"remaining_time":1.910298518},
{"learn":[0.1390593496],"iteration":98,"passed_time":0.2204114696,"remaining_time":1.894648087},
{"learn":[0.1386717887],"iteration":99,"passed_time":0.2210974634,"remaining_time":1.879328439},
{"learn":[0.1385360732],"iteration":100,"passed_time":0.2217871636,"remaining_time":1.864329722},
{"learn":[0.1380633432],"iteration":101,"passed_time":0.2224897462,"remaining_time":1.849718674},
{"learn":[0.1376744924],"iteration":102,"passed_time":0.2232118829,"remaining_time":1.835538493},
{"learn":[0.1373709355],"iteration":103,"passed_time":0.2238965744,"remaining_time":1.821312518},
{"learn":[0.1370805715],"iteration":104,"passed_time":0.2246150446,"remaining_time":1.807616312},
{"learn":[0.1367785967],"iteration":105,"passed_time":0.2253190598,"remaining_time":1.794049872},
{"learn":[0.1365565155],"iteration":106,"passed_time":0.2260372496,"remaining_time":1.780835527},
{"learn":[0.1362478049],"iteration":107,"passed_time":0.2267448609,"remaining_time":1.76777012},
{"learn":[0.1360066481],"iteration":108,"passed_time":0.227449387,"remaining_time":1.754907655},
{"learn":[0.1355806747],"iteration":109,"passed_time":0.2281738076,"remaining_time":1.742418167},
{"learn":[0.1352045721],"iteration":110,"passed_time":0.2289487161,"remaining_time":1.730522278},
{"learn":[0.13493936],"iteration":111,"passed_time":0.229666996,"remaining_time":1.718401274},
{"learn":[0.1346335909],"iteration":112,"passed_time":0.2303498043,"remaining_time":1.706219347},
{"learn":[0.1342811153],"iteration":113,"passed_time":0.231060511,"remaining_time":1.694443748},
{"learn":[0.1338976581],"iteration":114,"passed_time":0.2317775188,"remaining_time":1.682906332},
{"learn":[0.1336729511],"iteration":115,"passed_time":0.2324982931,"remaining_time":1.671582555},
{"learn":[0.1332439696],"iteration":116,"passed_time":0.2332077376,"remaining_time":1.660359363},
{"learn":[0.1329981264],"iteration":117,"passed_time":0.2339433678,"remaining_time":1.649499},
{"learn":[0.1325290645],"iteration":118,"passed_time":0.2347351957,"remaining_time":1.639201241},
{"learn":[0.1323249296],"iteration":119,"passed_time":0.2354371372,"remaining_time":1.628440199},
{"learn":[0.132009144],"iteration":120,"passed_time":0.236135202,"remaining_time":1.617818863},
{"learn":[0.1317236197],"iteration":121,"passed_time":0.2368299009,"remaining_time":1.60733736},
{"learn":[0.1312906308],"iteration":122,"passed_time":0.2375709305,"remaining_time":1.5973265},
{"learn":[0.1310342647],"iteration":123,"passed_time":0.2382686346,"remaining_time":1.58717655},
{"learn":[0.130666762],"iteration":124,"passed_time":0.238963043,"remaining_time":1.577156084},
{"learn":[0.1303238413],"iteration":125,"passed_time":0.2397001657,"remaining_time":1.567562989},
{"learn":[0.1301482174],"iteration":126,"passed_time":0.2403854182,"remaining_time":1.557773222},
{"learn":[0.1299376612],"iteration":127,"passed_time":0.2410797565,"remaining_time":1.548184061},
{"learn":[0.129821009],"iteration":128,"passed_time":0.241782279,"remaining_time":1.538784892},
{"learn":[0.1293963955],"iteration":129,"passed_time":0.2425439545,"remaining_time":1.529892636},
{"learn":[0.1291741838],"iteration":130,"passed_time":0.2432633263,"remaining_time":1.520860033},
{"learn":[0.1289570825],"iteration":131,"passed_time":0.2440162666,"remaining_time":1.51216141},
{"learn":[0.1288681546],"iteration":132,"passed_time":0.2447329338,"remaining_time":1.50335945},
{"learn":[0.1286272615],"iteration":133,"passed_time":0.2455452073,"remaining_time":1.495260367},
{"learn":[0.1282314718],"iteration":134,"passed_time":0.2462514463,"remaining_time":1.486629102},
{"learn":[0.1279974017],"iteration":135,"passed_time":0.2469480385,"remaining_time":1.478056642},
{"learn":[0.127835886],"iteration":136,"passed_time":0.2476259882,"remaining_time":1.469488529},
{"learn":[0.1277146968],"iteration":137,"passed_time":0.2483579821,"remaining_time":1.461352764},
{"learn":[0.1273997286],"iteration":138,"passed_time":0.2490626383,"remaining_time":1.453164026},
{"learn":[0.1271016528],"iteration":139,"passed_time":0.2497653311,"remaining_time":1.445070844},
{"learn":[0.1267671588],"iteration":140,"passed_time":0.2504642674,"remaining_time":1.437060939},
{"learn":[0.1265741224],"iteration":141,"passed_time":0.2511462642,"remaining_time":1.429057616},
{"learn":[0.1263450427],"iteration":142,"passed_time":0.251993759,"remaining_time":1.422090654},
{"learn":[0.1261441678],"iteration":143,"passed_time":0.2527057681,"remaining_time":1.414450341},
{"learn":[0.1258860503],"iteration":144,"passed_time":0.2534297279,"remaining_time":1.406971938},
{"learn":[0.1256680702],"iteration":145,"passed_time":0.2541259294,"remaining_time":1.3994332},
{"learn":[0.1253558611],"iteration":146,"passed_time":0.2548320683,"remaining_time":1.392041842},
{"learn":[0.1250911458],"iteration":147,"passed_time":0.2555192341,"remaining_time":1.384638012},
{"learn":[0.1247940994],"iteration":148,"passed_time":0.2562339077,"remaining_time":1.377472215},
{"learn":[0.1246498891],"iteration":149,"passed_time":0.2569480104,"remaining_time":1.370389389},
{"learn":[0.1242401819],"iteration":150,"passed_time":0.2577555256,"remaining_time":1.363885199},
{"learn":[0.1240528434],"iteration":151,"passed_time":0.2585144764,"remaining_time":1.357201001},
{"learn":[0.1239869658],"iteration":152,"passed_time":0.2592811806,"remaining_time":1.350634647},
{"learn":[0.1236836481],"iteration":153,"passed_time":0.2599888621,"remaining_time":1.343838534},
{"learn":[0.123411842],"iteration":154,"passed_time":0.2607377052,"remaining_time":1.337332101},
{"learn":[0.1232417704],"iteration":155,"passed_time":0.2614736259,"remaining_time":1.330833711},
{"learn":[0.1229560619],"iteration":156,"passed_time":0.2622120308,"remaining_time":1.324421277},
{"learn":[0.1227023363],"iteration":157,"passed_time":0.2629101257,"remaining_time":1.317878605},
{"learn":[0.1225112247],"iteration":158,"passed_time":0.2636420594,"remaining_time":1.311577792},
{"learn":[0.1224162979],"iteration":159,"passed_time":0.264385984,"remaining_time":1.305405796},
{"learn":[0.1221401267],"iteration":160,"passed_time":0.2651158941,"remaining_time":1.29923255},
{"learn":[0.1218574362],"iteration":161,"passed_time":0.265831219,"remaining_time":1.293055559},
{"learn":[0.1217524912],"iteration":162,"passed_time":0.266519076,"remaining_time":1.286812962},
{"learn":[0.1214992932],"iteration":163,"passed_time":0.2672924518,"remaining_time":1.28104797},
{"learn":[0.1213131245],"iteration":164,"passed_time":0.2680425571,"remaining_time":1.275232772},
{"learn":[0.1209432],"iteration":165,"passed_time":0.2687920213,"remaining_time":1.269475571},
{"learn":[0.1207268455],"iteration":166,"passed_time":0.2695172734,"remaining_time":1.263664821},
{"learn":[0.1204856979],"iteration":167,"passed_time":0.2702785081,"remaining_time":1.258082103},
{"learn":[0.1203204048],"iteration":168,"passed_time":0.2709830842,"remaining_time":1.252294608},
{"learn":[0.1199984436],"iteration":169,"passed_time":0.2717930738,"remaining_time":1.247050574},
{"learn":[0.1198233194],"iteration":170,"passed_time":0.2725266503,"remaining_time":1.241510296},
{"learn":[0.1196992965],"iteration":171,"passed_time":0.2732311463,"remaining_time":1.235894371},
{"learn":[0.1195192808],"iteration":172,"passed_time":0.2739727068,"remaining_time":1.230501694},
{"learn":[0.1192268483],"iteration":173,"passed_time":0.2746753595,"remaining_time":1.22498896},
{"learn":[0.1191979564],"iteration":174,"passed_time":0.2753837422,"remaining_time":1.219556573},
{"learn":[0.1189494547],"iteration":175,"passed_time":0.2760939982,"remaining_time":1.214186106},
{"learn":[0.1186647145],"iteration":176,"passed_time":0.2768404071,"remaining_time":1.209026185},
{"learn":[0.1183704727],"iteration":177,"passed_time":0.2775671718,"remaining_time":1.203830655},
{"learn":[0.1180031915],"iteration":178,"passed_time":0.2783089727,"remaining_time":1.198749821},
{"learn":[0.1177564881],"iteration":179,"passed_time":0.279017095,"remaining_time":1.193573129},
{"learn":[0.117631515],"iteration":180,"passed_time":0.2797103013,"remaining_time":1.18838244},
{"learn":[0.1174162169],"iteration":181,"passed_time":0.2805343353,"remaining_time":1.183793239},
{"learn":[0.1171543329],"iteration":182,"passed_time":0.2812687233,"remaining_time":1.178869458},
{"learn":[0.1169139205],"iteration":183,"passed_time":0.2819590946,"remaining_time":1.17380797},
{"learn":[0.1166543038],"iteration":184,"passed_time":0.2826583014,"remaining_time":1.168830273},
{"learn":[0.1164607542],"iteration":185,"passed_time":0.2833517481,"remaining_time":1.163874922},
{"learn":[0.1162109192],"iteration":186,"passed_time":0.284061904,"remaining_time":1.15903333},
{"learn":[0.1160285019],"iteration":187,"passed_time":0.2847561922,"remaining_time":1.154171375},
{"learn":[0.1157710289],"iteration":188,"passed_time":0.285447395,"remaining_time":1.149341098},
{"learn":[0.1156326236],"iteration":189,"passed_time":0.2861734485,"remaining_time":1.144693794},
{"learn":[0.1155883268],"iteration":190,"passed_time":0.2868891439,"remaining_time":1.140046389},
{"learn":[0.1153935154],"iteration":191,"passed_time":0.2876177518,"remaining_time":1.135490916},
{"learn":[0.1151935041],"iteration":192,"passed_time":0.2884041103,"remaining_time":1.131201614},
{"learn":[0.1149745522],"iteration":193,"passed_time":0.2891388889,"remaining_time":1.126747423},
{"learn":[0.1147446169],"iteration":194,"passed_time":0.2898534324,"remaining_time":1.122253033},
{"learn":[0.1146461206],"iteration":195,"passed_time":0.2905490028,"remaining_time":1.117724225},
{"learn":[0.1144371802],"iteration":196,"passed_time":0.2913803194,"remaining_time":1.113753201},
{"learn":[0.1143910018],"iteration":197,"passed_time":0.2921241338,"remaining_time":1.109481559},
{"learn":[0.1141579313],"iteration":198,"passed_time":0.2928475427,"remaining_time":1.105168365},
{"learn":[0.1139466152],"iteration":199,"passed_time":0.2935661632,"remaining_time":1.100873112},
{"learn":[0.1138084723],"iteration":200,"passed_time":0.2942655804,"remaining_time":1.096541889},
{"learn":[0.1135988736],"iteration":201,"passed_time":0.2949685136,"remaining_time":1.092259644},
{"learn":[0.1134636521],"iteration":202,"passed_time":0.295657172,"remaining_time":1.087960135},
{"learn":[0.1134008188],"iteration":203,"passed_time":0.2963176213,"remaining_time":1.08359287},
{"learn":[0.1133288487],"iteration":204,"passed_time":0.297020815,"remaining_time":1.079417108},
{"learn":[0.1132527732],"iteration":205,"passed_time":0.2977006781,"remaining_time":1.075190799},
{"learn":[0.1130224359],"iteration":206,"passed_time":0.2984041022,"remaining_time":1.071083323},
{"learn":[0.112882384],"iteration":207,"passed_time":0.2991842699,"remaining_time":1.067282347},
{"learn":[0.1126548523],"iteration":208,"passed_time":0.2999275934,"remaining_time":1.063379649},
{"learn":[0.1124706999],"iteration":209,"passed_time":0.3006787806,"remaining_time":1.059534751},
{"learn":[0.1123077261],"iteration":210,"passed_time":0.301416855,"remaining_time":1.05567325},
{"learn":[0.1120858887],"iteration":211,"passed_time":0.3021437299,"remaining_time":1.05180223},
{"learn":[0.1119533957],"iteration":212,"passed_time":0.3028361649,"remaining_time":1.047841566},
{"learn":[0.1118441969],"iteration":213,"passed_time":0.3035412619,"remaining_time":1.043954994},
{"learn":[0.1117098336],"iteration":214,"passed_time":0.3042592213,"remaining_time":1.040141989},
{"learn":[0.1115703663],"iteration":215,"passed_time":0.3049889712,"remaining_time":1.036397708},
{"learn":[0.1115047369],"iteration":216,"passed_time":0.3057016314,"remaining_time":1.032623483},
{"learn":[0.1113239928],"iteration":217,"passed_time":0.3064411683,"remaining_time":1.028967593},
{"learn":[0.1111600637],"iteration":218,"passed_time":0.3071621229,"remaining_time":1.02527631},
{"learn":[0.11109644],"iteration":219,"passed_time":0.307852885,"remaining_time":1.021511846},
{"learn":[0.1109613933],"iteration":220,"passed_time":0.3085650242,"remaining_time":1.017845713},
{"learn":[0.1108185796],"iteration":221,"passed_time":0.3092806696,"remaining_time":1.014217691},
{"learn":[0.1106612168],"iteration":222,"passed_time":0.3100076547,"remaining_time":1.010652758},
{"learn":[0.1105005991],"iteration":223,"passed_time":0.3107153462,"remaining_time":1.007050631},
{"learn":[0.1103734991],"iteration":224,"passed_time":0.3114381741,"remaining_time":1.003523005},
{"learn":[0.11026154],"iteration":225,"passed_time":0.3121298577,"remaining_time":0.9999204292},
{"learn":[0.1101453859],"iteration":226,"passed_time":0.3128407749,"remaining_time":0.9964047588},
{"learn":[0.110055442],"iteration":227,"passed_time":0.3135303248,"remaining_time":0.9928460287},
{"learn":[0.1098187614],"iteration":228,"passed_time":0.314252742,"remaining_time":0.9894158383},
{"learn":[0.1097660741],"iteration":229,"passed_time":0.3149340676,"remaining_time":0.9858805595},
{"learn":[0.1096324684],"iteration":230,"passed_time":0.315611206,"remaining_time":0.9823569572},
{"learn":[0.1094965995],"iteration":231,"passed_time":0.3164111233,"remaining_time":0.979237873},
{"learn":[0.1092203624],"iteration":232,"passed_time":0.3172283454,"remaining_time":0.9761919471},
{"learn":[0.10900479],"iteration":233,"passed_time":0.317959618,"remaining_time":0.972902079},
{"learn":[0.1088327087],"iteration":234,"passed_time":0.3186755238,"remaining_time":0.9695872321},
{"learn":[0.1087793379],"iteration":235,"passed_time":0.3193618682,"remaining_time":0.9662049741},
{"learn":[0.108632249],"iteration":236,"passed_time":0.3200688184,"remaining_time":0.962907458},
{"learn":[0.1084726425],"iteration":237,"passed_time":0.3207762295,"remaining_time":0.9596330898},
{"learn":[0.1083743866],"iteration":238,"passed_time":0.3215116492,"remaining_time":0.9564635256},
{"learn":[0.1083510709],"iteration":239,"passed_time":0.3222336256,"remaining_time":0.9532744758},
{"learn":[0.1082288486],"iteration":240,"passed_time":0.322955622,"remaining_time":0.9501059586},
{"learn":[0.1081568979],"iteration":241,"passed_time":0.3236657879,"remaining_time":0.9469230488},
{"learn":[0.1079427674],"iteration":242,"passed_time":0.3244852138,"remaining_time":0.9440783793},
{"learn":[0.1077457523],"iteration":243,"passed_time":0.325203634,"remaining_time":0.9409580558},
{"learn":[0.1075449596],"iteration":244,"passed_time":0.3259334541,"remaining_time":0.9378901433},
{"learn":[0.1074625301],"iteration":245,"passed_time":0.3266522148,"remaining_time":0.9348095904},
{"learn":[0.1072757631],"iteration":246,"passed_time":0.3273875344,"remaining_time":0.9317952903},
{"learn":[0.1072228058],"iteration":247,"passed_time":0.328088324,"remaining_time":0.9287016267},
{"learn":[0.1071934041],"iteration":248,"passed_time":0.328796306,"remaining_time":0.9256474317},
{"learn":[0.1071141475],"iteration":249,"passed_time":0.3295313451,"remaining_time":0.9226877663},
{"learn":[0.106950374],"iteration":250,"passed_time":0.3302682775,"remaining_time":0.9197510995},
{"learn":[0.1068895131],"iteration":251,"passed_time":0.3310072034,"remaining_time":0.9168374126},
{"learn":[0.1067606105],"iteration":252,"passed_time":0.3317649215,"remaining_time":0.913992689},
{"learn":[0.1066057085],"iteration":253,"passed_time":0.3326613014,"remaining_time":0.9115443535},
{"learn":[0.106560785],"iteration":254,"passed_time":0.3334303898,"remaining_time":0.9087612584},
{"learn":[0.1065206059],"iteration":255,"passed_time":0.3341268818,"remaining_time":0.9057970937},
{"learn":[0.1063757534],"iteration":256,"passed_time":0.3348804131,"remaining_time":0.9030043824},
{"learn":[0.106196645],"iteration":257,"passed_time":0.3355921216,"remaining_time":0.900115303},
{"learn":[0.1060796352],"iteration":258,"passed_time":0.3363310175,"remaining_time":0.8973155717},
{"learn":[0.1059409896],"iteration":259,"passed_time":0.3370388592,"remaining_time":0.8944492803},
{"learn":[0.105926505],"iteration":260,"passed_time":0.337712201,"remaining_time":0.8915084539},
{"learn":[0.1058222881],"iteration":261,"passed_time":0.3384221765,"remaining_time":0.8886811352},
{"learn":[0.1058031285],"iteration":262,"passed_time":0.3391110453,"remaining_time":0.8858147836},
{"learn":[0.1056774126],"iteration":263,"passed_time":0.3398359567,"remaining_time":0.8830585846},
{"learn":[0.1056548564],"iteration":264,"passed_time":0.3405312467,"remaining_time":0.8802411471},
{"learn":[0.1055237941],"iteration":265,"passed_time":0.341277916,"remaining_time":0.8775717841},
{"learn":[0.1053989214],"iteration":266,"passed_time":0.3419915379,"remaining_time":0.874832286},
{"learn":[0.1052606247],"iteration":267,"passed_time":0.3427226001,"remaining_time":0.8721522882},
{"learn":[0.1051114174],"iteration":268,"passed_time":0.3434343086,"remaining_time":0.8694377849},
{"learn":[0.105081856],"iteration":269,"passed_time":0.3441311412,"remaining_time":0.8667006519},
{"learn":[0.1050750377],"iteration":270,"passed_time":0.3448473676,"remaining_time":0.8640271682},
{"learn":[0.1050244074],"iteration":271,"passed_time":0.3455881964,"remaining_time":0.8614294012},
{"learn":[0.1048163535],"iteration":272,"passed_time":0.3463557324,"remaining_time":0.8589114684},
{"learn":[0.1047134318],"iteration":273,"passed_time":0.3471539014,"remaining_time":0.8564818882},
{"learn":[0.1045616668],"iteration":274,"passed_time":0.3478960229,"remaining_time":0.8539266015},
{"learn":[0.1044873003],"iteration":275,"passed_time":0.348633937,"remaining_time":0.8513741794},
{"learn":[0.1044282769],"iteration":276,"passed_time":0.3493481899,"remaining_time":0.8487773712},
{"learn":[0.1041902117],"iteration":277,"passed_time":0.3500839403,"remaining_time":0.8462460714},
{"learn":[0.1041414471],"iteration":278,"passed_time":0.3507809732,"remaining_time":0.843634527},
{"learn":[0.1040072608],"iteration":279,"passed_time":0.3515255089,"remaining_time":0.8411503248},
{"learn":[0.1038729452],"iteration":280,"passed_time":0.352258825,"remaining_time":0.8386517933},
{"learn":[0.1038461664],"iteration":281,"passed_time":0.3529607966,"remaining_time":0.8360915323},
{"learn":[0.1038183669],"iteration":282,"passed_time":0.3536524798,"remaining_time":0.8335201556},
{"learn":[0.1038047847],"iteration":283,"passed_time":0.3543261822,"remaining_time":0.8309198497},
{"learn":[0.103680885],"iteration":284,"passed_time":0.3550449229,"remaining_time":0.8284381535},
{"learn":[0.1035122875],"iteration":285,"passed_time":0.3557636336,"remaining_time":0.8259687158},
{"learn":[0.1033270941],"iteration":286,"passed_time":0.3564944454,"remaining_time":0.8235394331},
{"learn":[0.1032290971],"iteration":287,"passed_time":0.3572880865,"remaining_time":0.8212663654},
{"learn":[0.1031250762],"iteration":288,"passed_time":0.358011846,"remaining_time":0.818843703},
{"learn":[0.1030383694],"iteration":289,"passed_time":0.3587620118,"remaining_time":0.8164928545},
{"learn":[0.1028889304],"iteration":290,"passed_time":0.3594749926,"remaining_time":0.8140687976},
{"learn":[0.1027622472],"iteration":291,"passed_time":0.36025505,"remaining_time":0.8118076127},
{"learn":[0.1026130363],"iteration":292,"passed_time":0.3610240382,"remaining_time":0.809531717},
{"learn":[0.1024846863],"iteration":293,"passed_time":0.3617753356,"remaining_time":0.8072265992},
{"learn":[0.102407396],"iteration":294,"passed_time":0.3624955289,"remaining_time":0.804862954},
{"learn":[0.1022455957],"iteration":295,"passed_time":0.363320204,"remaining_time":0.8027412615},
{"learn":[0.1021638349],"iteration":296,"passed_time":0.3640658015,"remaining_time":0.8004544389},
{"learn":[0.1021051675],"iteration":297,"passed_time":0.3648032347,"remaining_time":0.7981600975},
{"learn":[0.1020421003],"iteration":298,"passed_time":0.3655046353,"remaining_time":0.7957977177},
{"learn":[0.1019934805],"iteration":299,"passed_time":0.3663231597,"remaining_time":0.7937001794},
{"learn":[0.1018354008],"iteration":300,"passed_time":0.367059441,"remaining_time":0.7914338113},
{"learn":[0.1016929834],"iteration":301,"passed_time":0.3677672327,"remaining_time":0.7891164463},
{"learn":[0.1016806504],"iteration":302,"passed_time":0.3684487186,"remaining_time":0.7867535345},
{"learn":[0.1015917661],"iteration":303,"passed_time":0.3692036523,"remaining_time":0.7845577612},
{"learn":[0.1015854257],"iteration":304,"passed_time":0.3700712822,"remaining_time":0.7826097607},
{"learn":[0.1014027877],"iteration":305,"passed_time":0.3707834916,"remaining_time":0.7803417274},
{"learn":[0.1013492298],"iteration":306,"passed_time":0.3714808451,"remaining_time":0.7780527147},
{"learn":[0.1012187672],"iteration":307,"passed_time":0.3722226861,"remaining_time":0.7758667677},
{"learn":[0.1012134927],"iteration":308,"passed_time":0.3729098418,"remaining_time":0.7735767269},
{"learn":[0.1010527714],"iteration":309,"passed_time":0.3736342424,"remaining_time":0.7713739199},
{"learn":[0.1010328751],"iteration":310,"passed_time":0.3743305241,"remaining_time":0.7691228454},
{"learn":[0.100880674],"iteration":311,"passed_time":0.3750622875,"remaining_time":0.7669542931},
{"learn":[0.1007730789],"iteration":312,"passed_time":0.3758188942,"remaining_time":0.7648454811},
{"learn":[0.1006712076],"iteration":313,"passed_time":0.376548584,"remaining_time":0.7626907625},
{"learn":[0.1005720031],"iteration":314,"passed_time":0.3774443628,"remaining_time":0.760879906},
{"learn":[0.1004422046],"iteration":315,"passed_time":0.3782146433,"remaining_time":0.7588230501},
{"learn":[0.1003782688],"iteration":316,"passed_time":0.3789306593,"remaining_time":0.7566659537},
{"learn":[0.1002651361],"iteration":317,"passed_time":0.3796597681,"remaining_time":0.7545439415},
{"learn":[0.1002580992],"iteration":318,"passed_time":0.3803896282,"remaining_time":0.7524321485},
{"learn":[0.1001788363],"iteration":319,"passed_time":0.3811241564,"remaining_time":0.7503381829},
{"learn":[0.1001178641],"iteration":320,"passed_time":0.3818394211,"remaining_time":0.7482149404},
{"learn":[0.1000890258],"iteration":321,"passed_time":0.3825050895,"remaining_time":0.7460037149},
{"learn":[0.1000329123],"iteration":322,"passed_time":0.3831975745,"remaining_time":0.7438541153},
{"learn":[0.1000225544],"iteration":323,"passed_time":0.3838692133,"remaining_time":0.7416732332},
{"learn":[0.09993161184],"iteration":324,"passed_time":0.384548235,"remaining_time":0.7395158365},
{"learn":[0.0997868568],"iteration":325,"passed_time":0.3852667553,"remaining_time":0.7374431145},
{"learn":[0.09968541857],"iteration":326,"passed_time":0.3859649303,"remaining_time":0.7353399131},
{"learn":[0.09954637529],"iteration":327,"passed_time":0.3866764084,"remaining_time":0.7332705062},
{"learn":[0.09947947719],"iteration":328,"passed_time":0.3873899301,"remaining_time":0.7312132115},
{"learn":[0.09932225346],"iteration":329,"passed_time":0.3881344857,"remaining_time":0.7292223672},
{"learn":[0.09930986595],"iteration":330,"passed_time":0.3889438041,"remaining_time":0.7273601654},
{"learn":[0.09922587543],"iteration":331,"passed_time":0.3896695471,"remaining_time":0.7253487352},
{"learn":[0.09909504476],"iteration":332,"passed_time":0.3903708575,"remaining_time":0.7232997569},
{"learn":[0.09900740122],"iteration":333,"passed_time":0.3911109955,"remaining_time":0.7213304587},
{"learn":[0.09899467967],"iteration":334,"passed_time":0.3918530067,"remaining_time":0.7193719377},
{"learn":[0.09887431565],"iteration":335,"passed_time":0.3925848903,"remaining_time":0.7174021508},
{"learn":[0.09876548787],"iteration":336,"passed_time":0.393304713,"remaining_time":0.7154177716},
{"learn":[0.0987583419],"iteration":337,"passed_time":0.3939922795,"remaining_time":0.7133824705},
{"learn":[0.09861523235],"iteration":338,"passed_time":0.3947330485,"remaining_time":0.7114510108},
{"learn":[0.09849466228],"iteration":339,"passed_time":0.3954654531,"remaining_time":0.7095115482},
{"learn":[0.09842940758],"iteration":340,"passed_time":0.3962669078,"remaining_time":0.7077024834},
{"learn":[0.09822745933],"iteration":341,"passed_time":0.3970844204,"remaining_time":0.7059278585},
{"learn":[0.09805853263],"iteration":342,"passed_time":0.3978263315,"remaining_time":0.7040250239},
{"learn":[0.09792309235],"iteration":343,"passed_time":0.3985665496,"remaining_time":0.7021259566},
{"learn":[0.09788842288],"iteration":344,"passed_time":0.3992532045,"remaining_time":0.7001396775},
{"learn":[0.09773291794],"iteration":345,"passed_time":0.399962268,"remaining_time":0.6982000285},
{"learn":[0.09756948435],"iteration":346,"passed_time":0.4007100793,"remaining_time":0.6963348065},
{"learn":[0.09754596683],"iteration":347,"passed_time":0.4014120108,"remaining_time":0.6943966394},
{"learn":[0.09750418313],"iteration":348,"passed_time":0.402109715,"remaining_time":0.6924582771},
{"learn":[0.09730335978],"iteration":349,"passed_time":0.4028491117,"remaining_time":0.6905984772},
{"learn":[0.09724947167],"iteration":350,"passed_time":0.4035413864,"remaining_time":0.6886646451},
{"learn":[0.09715375581],"iteration":351,"passed_time":0.4042610087,"remaining_time":0.6867843272},
{"learn":[0.09709803942],"iteration":352,"passed_time":0.4049478639,"remaining_time":0.6848551693},
{"learn":[0.09697698984],"iteration":353,"passed_time":0.4057447711,"remaining_time":0.6831183152},
{"learn":[0.09688524994],"iteration":354,"passed_time":0.4065022894,"remaining_time":0.6813207385},
{"learn":[0.09682642013],"iteration":355,"passed_time":0.4072009351,"remaining_time":0.6794307738},
{"learn":[0.09674480157],"iteration":356,"passed_time":0.4078974572,"remaining_time":0.6775439556},
{"learn":[0.09667766322],"iteration":357,"passed_time":0.408608144,"remaining_time":0.6756872101},
{"learn":[0.09654365923],"iteration":358,"passed_time":0.4094028569,"remaining_time":0.6739751767},
{"learn":[0.09653244132],"iteration":359,"passed_time":0.4100939395,"remaining_time":0.6720984009},
{"learn":[0.09644291449],"iteration":360,"passed_time":0.4108115183,"remaining_time":0.6702714245},
{"learn":[0.09634519544],"iteration":361,"passed_time":0.4115438026,"remaining_time":0.6684744639},
{"learn":[0.09633639928],"iteration":362,"passed_time":0.4121992632,"remaining_time":0.6665591391},
{"learn":[0.0962167162],"iteration":363,"passed_time":0.412941595,"remaining_time":0.6647905898},
{"learn":[0.09620236863],"iteration":364,"passed_time":0.4136764939,"remaining_time":0.6630157505},
{"learn":[0.09613167207],"iteration":365,"passed_time":0.4143976689,"remaining_time":0.6612246957},
{"learn":[0.09612689838],"iteration":366,"passed_time":0.4150658517,"remaining_time":0.6593552902},
{"learn":[0.09610112866],"iteration":367,"passed_time":0.4158175798,"remaining_time":0.657624542},
{"learn":[0.09597642848],"iteration":368,"passed_time":0.4165204529,"remaining_time":0.6558221766},
{"learn":[0.09583834982],"iteration":369,"passed_time":0.4172403156,"remaining_time":0.6540523867},
{"learn":[0.09580526911],"iteration":370,"passed_time":0.4179345738,"remaining_time":0.6522482971},
{"learn":[0.09575597638],"iteration":371,"passed_time":0.4186171717,"remaining_time":0.650432057},
{"learn":[0.09567913484],"iteration":372,"passed_time":0.4193364934,"remaining_time":0.6486787043},
{"learn":[0.09565146478],"iteration":373,"passed_time":0.4200395569,"remaining_time":0.6469058416},
{"learn":[0.09556698318],"iteration":374,"passed_time":0.420744123,"remaining_time":0.6451409886},
{"learn":[0.09549836221],"iteration":375,"passed_time":0.4215410794,"remaining_time":0.643522818},
{"learn":[0.09536054188],"iteration":376,"passed_time":0.4225243805,"remaining_time":0.6421922283},
{"learn":[0.0952316733],"iteration":377,"passed_time":0.4232656505,"remaining_time":0.6404972277},
{"learn":[0.09516133468],"iteration":378,"passed_time":0.4240151748,"remaining_time":0.6388196961},
{"learn":[0.09507267008],"iteration":379,"passed_time":0.4247845938,"remaining_time":0.6371768906},
{"learn":[0.09493305359],"iteration":380,"passed_time":0.4255409099,"remaining_time":0.6355191017},
{"learn":[0.09490966279],"iteration":381,"passed_time":0.4262401868,"remaining_time":0.6337812201},
{"learn":[0.0947865639],"iteration":382,"passed_time":0.4269521357,"remaining_time":0.6320675221},
{"learn":[0.09469701353],"iteration":383,"passed_time":0.4276779788,"remaining_time":0.6303795209},
{"learn":[0.09460885953],"iteration":384,"passed_time":0.428391791,"remaining_time":0.6286788621},
{"learn":[0.09445503314],"iteration":385,"passed_time":0.4291001737,"remaining_time":0.6269753834},
{"learn":[0.09435132749],"iteration":386,"passed_time":0.4298026862,"remaining_time":0.6252685074},
{"learn":[0.09422852869],"iteration":387,"passed_time":0.4305224488,"remaining_time":0.6235917943},
{"learn":[0.0941496428],"iteration":388,"passed_time":0.4312228977,"remaining_time":0.6218921481},
{"learn":[0.09410789079],"iteration":389,"passed_time":0.4319359686,"remaining_time":0.6202157497},
{"learn":[0.0940499222],"iteration":390,"passed_time":0.4326665403,"remaining_time":0.6185692994},
{"learn":[0.09393724988],"iteration":391,"passed_time":0.4334227062,"remaining_time":0.6169639543},
{"learn":[0.09385136833],"iteration":392,"passed_time":0.4341336133,"remaining_time":0.6152987853},
{"learn":[0.09367950744],"iteration":393,"passed_time":0.4348714774,"remaining_time":0.613676501},
{"learn":[0.09358720307],"iteration":394,"passed_time":0.43570051,"remaining_time":0.6121867926},
{"learn":[0.09347220987],"iteration":395,"passed_time":0.4364235383,"remaining_time":0.6105521217},
{"learn":[0.09340135678],"iteration":396,"passed_time":0.4371633252,"remaining_time":0.6089453875},
{"learn":[0.0933887332],"iteration":397,"passed_time":0.4378563312,"remaining_time":0.6072781277},
{"learn":[0.09324512405],"iteration":398,"passed_time":0.4385783176,"remaining_time":0.6056557719},
{"learn":[0.09311260221],"iteration":399,"passed_time":0.4393614504,"remaining_time":0.6041219943},
{"learn":[0.0930651285],"iteration":400,"passed_time":0.4400638627,"remaining_time":0.602481448},
{"learn":[0.09290478827],"iteration":401,"passed_time":0.4407661148,"remaining_time":0.6008453505},
{"learn":[0.0928473704],"iteration":402,"passed_time":0.4414688777,"remaining_time":0.5992145809},
{"learn":[0.09284302926],"iteration":403,"passed_time":0.4421462665,"remaining_time":0.5975541127},
{"learn":[0.09270381182],"iteration":404,"passed_time":0.4428501214,"remaining_time":0.5959341139},
{"learn":[0.09258492929],"iteration":405,"passed_time":0.4435407532,"remaining_time":0.5943009107},
{"learn":[0.09254893926],"iteration":406,"passed_time":0.4442649134,"remaining_time":0.5927170712},
{"learn":[0.09243381379],"iteration":407,"passed_time":0.444957158,"remaining_time":0.5910950481},
{"learn":[0.09239096472],"iteration":408,"passed_time":0.4456465377,"remaining_time":0.5894737821},
{"learn":[0.09232036636],"iteration":409,"passed_time":0.4463836103,"remaining_time":0.587919877},
{"learn":[0.09222875789],"iteration":410,"passed_time":0.447114923,"remaining_time":0.5863623929},
{"learn":[0.09215146965],"iteration":411,"passed_time":0.4478351062,"remaining_time":0.5847943863},
{"learn":[0.09201983404],"iteration":412,"passed_time":0.4486081819,"remaining_time":0.5832992584},
{"learn":[0.09191550776],"iteration":413,"passed_time":0.4493408369,"remaining_time":0.5817552864},
{"learn":[0.09185611597],"iteration":414,"passed_time":0.4500589967,"remaining_time":0.5801965379},
{"learn":[0.0917315517],"iteration":415,"passed_time":0.4507836477,"remaining_time":0.5786501631},
{"learn":[0.09166118153],"iteration":416,"passed_time":0.4514881937,"remaining_time":0.5770820318},
{"learn":[0.09158812018],"iteration":417,"passed_time":0.4521949737,"remaining_time":0.5755208756},
{"learn":[0.09146978591],"iteration":418,"passed_time":0.4529102684,"remaining_time":0.5739745884},
{"learn":[0.09139853677],"iteration":419,"passed_time":0.4536228785,"remaining_time":0.5724288705},
{"learn":[0.09128962593],"iteration":420,"passed_time":0.4543543214,"remaining_time":0.5709107744},
{"learn":[0.09121075545],"iteration":421,"passed_time":0.4550792429,"remaining_time":0.569388247},
{"learn":[0.09109954922],"iteration":422,"passed_time":0.455798194,"remaining_time":0.5678620526},
{"learn":[0.09104475164],"iteration":423,"passed_time":0.4564896473,"remaining_time":0.566305553},
{"learn":[0.0909844443],"iteration":424,"passed_time":0.4571958462,"remaining_time":0.5647713394},
{"learn":[0.09088184874],"iteration":425,"passed_time":0.4579286915,"remaining_time":0.5632737895},
{"learn":[0.09087168267],"iteration":426,"passed_time":0.458613403,"remaining_time":0.561720866},
{"learn":[0.0907374725],"iteration":427,"passed_time":0.4593280667,"remaining_time":0.5602085299},
{"learn":[0.09065348053],"iteration":428,"passed_time":0.4600496524,"remaining_time":0.5587083191},
{"learn":[0.09062389973],"iteration":429,"passed_time":0.4607397533,"remaining_time":0.5571736551},
{"learn":[0.09053154068],"iteration":430,"passed_time":0.4614566709,"remaining_time":0.5556752023},
{"learn":[0.09042943782],"iteration":431,"passed_time":0.4621657348,"remaining_time":0.5541709505},
{"learn":[0.0903692593],"iteration":432,"passed_time":0.4629228619,"remaining_time":0.5527277589},
{"learn":[0.09026256786],"iteration":433,"passed_time":0.4636365839,"remaining_time":0.5512361228},
{"learn":[0.09018211891],"iteration":434,"passed_time":0.4643369226,"remaining_time":0.5497322188},
{"learn":[0.09013275139],"iteration":435,"passed_time":0.4650375118,"remaining_time":0.548232296},
{"learn":[0.09004445412],"iteration":436,"passed_time":0.4657492203,"remaining_time":0.5467490847},
{"learn":[0.08997319035],"iteration":437,"passed_time":0.4665067786,"remaining_time":0.5453229924},
{"learn":[0.0898970097],"iteration":438,"passed_time":0.467229897,"remaining_time":0.5438598573},
{"learn":[0.0898501476],"iteration":439,"passed_time":0.467939612,"remaining_time":0.5423845503},
{"learn":[0.08977251984],"iteration":440,"passed_time":0.4686997448,"remaining_time":0.5409709073},
{"learn":[0.08971882873],"iteration":441,"passed_time":0.4694180047,"remaining_time":0.5395120959},
{"learn":[0.0896425274],"iteration":442,"passed_time":0.4701457011,"remaining_time":0.5380674276},
{"learn":[0.08958083282],"iteration":443,"passed_time":0.4708468612,"remaining_time":0.5365957473},
{"learn":[0.08951272171],"iteration":444,"passed_time":0.4715528498,"remaining_time":0.5351330093},
{"learn":[0.08950539219],"iteration":445,"passed_time":0.4722233967,"remaining_time":0.5336336142},
{"learn":[0.08943110096],"iteration":446,"passed_time":0.4729387115,"remaining_time":0.5321883039},
{"learn":[0.08933903854],"iteration":447,"passed_time":0.473659035,"remaining_time":0.5307518651},
{"learn":[0.08926450422],"iteration":448,"passed_time":0.4743682692,"remaining_time":0.5293062424},
{"learn":[0.08915953736],"iteration":449,"passed_time":0.4751425466,"remaining_time":0.5279361629},
{"learn":[0.08904074268],"iteration":450,"passed_time":0.4758810317,"remaining_time":0.5265291237},
{"learn":[0.0889865151],"iteration":451,"passed_time":0.476632289,"remaining_time":0.5251391149},
{"learn":[0.08892460762],"iteration":452,"passed_time":0.4774064162,"remaining_time":0.5237770173},
{"learn":[0.08880417146],"iteration":453,"passed_time":0.4781960202,"remaining_time":0.5224344186},
{"learn":[0.08876275511],"iteration":454,"passed_time":0.4789041725,"remaining_time":0.5210056383},
{"learn":[0.08863614192],"iteration":455,"passed_time":0.479657774,"remaining_time":0.5196292551},
{"learn":[0.0885568746],"iteration":456,"passed_time":0.4803737299,"remaining_time":0.5182149865},
{"learn":[0.08846885469],"iteration":457,"passed_time":0.4811011758,"remaining_time":0.5168161102},
{"learn":[0.08841973818],"iteration":458,"passed_time":0.4818313364,"remaining_time":0.5154230635},
{"learn":[0.08833904624],"iteration":459,"passed_time":0.482569511,"remaining_time":0.5140414356},
{"learn":[0.08833534589],"iteration":460,"passed_time":0.4832456776,"remaining_time":0.5125968251},
{"learn":[0.08831401436],"iteration":461,"passed_time":0.4839556231,"remaining_time":0.5111912209},
{"learn":[0.08827638386],"iteration":462,"passed_time":0.4846322205,"remaining_time":0.5097535451},
{"learn":[0.08821327236],"iteration":463,"passed_time":0.4853567513,"remaining_time":0.5083693559},
{"learn":[0.08815614602],"iteration":464,"passed_time":0.4860561885,"remaining_time":0.506961831},
{"learn":[0.08815296663],"iteration":465,"passed_time":0.4867201339,"remaining_time":0.5055204824},
{"learn":[0.08806400473],"iteration":466,"passed_time":0.4874243594,"remaining_time":0.5041241233},
{"learn":[0.08806028607],"iteration":467,"passed_time":0.4881699268,"remaining_time":0.5027733007},
{"learn":[0.08795573793],"iteration":468,"passed_time":0.4889033731,"remaining_time":0.5014126279},
{"learn":[0.08784692982],"iteration":469,"passed_time":0.489626231,"remaining_time":0.5000438104},
{"learn":[0.08779847027],"iteration":470,"passed_time":0.4903466647,"remaining_time":0.4986752705},
{"learn":[0.0876948662],"iteration":471,"passed_time":0.4910864621,"remaining_time":0.4973290867},
{"learn":[0.08766871604],"iteration":472,"passed_time":0.4917707529,"remaining_time":0.4959294908},
{"learn":[0.08757614671],"iteration":473,"passed_time":0.4924617654,"remaining_time":0.4945396632},
{"learn":[0.08748887252],"iteration":474,"passed_time":0.4932266765,"remaining_time":0.4932266765},
{"learn":[0.08740601014],"iteration":475,"passed_time":0.4939341677,"remaining_time":0.4918588141},
{"learn":[0.08735838468],"iteration":476,"passed_time":0.494651466,"remaining_time":0.4905034453},
{"learn":[0.08727734108],"iteration":477,"passed_time":0.4954143335,"remaining_time":0.4891957435},
{"learn":[0.08717864622],"iteration":478,"passed_time":0.4961382332,"remaining_time":0.4878519997},
{"learn":[0.08715542834],"iteration":479,"passed_time":0.4968326617,"remaining_time":0.4864819812},
{"learn":[0.08707404045],"iteration":480,"passed_time":0.4975320988,"remaining_time":0.4851196556},
{"learn":[0.0869936107],"iteration":481,"passed_time":0.4982486858,"remaining_time":0.4837767323},
{"learn":[0.08695467226],"iteration":482,"passed_time":0.4989433146,"remaining_time":0.4824151717},
{"learn":[0.08695084208],"iteration":483,"passed_time":0.4996499844,"remaining_time":0.4810679602},
{"learn":[0.08689901794],"iteration":484,"passed_time":0.5003783619,"remaining_time":0.4797442026},
{"learn":[0.08684452104],"iteration":485,"passed_time":0.5010875761,"remaining_time":0.4784045994},
{"learn":[0.08680233944],"iteration":486,"passed_time":0.5018224849,"remaining_time":0.4770920134},
{"learn":[0.08674802891],"iteration":487,"passed_time":0.5025491595,"remaining_time":0.4757739994},
{"learn":[0.08670186233],"iteration":488,"passed_time":0.5032604373,"remaining_time":0.4744438887},
{"learn":[0.08668403566],"iteration":489,"passed_time":0.5039575604,"remaining_time":0.4731030159},
{"learn":[0.08662992743],"iteration":490,"passed_time":0.5046962358,"remaining_time":0.4718036095},
{"learn":[0.08653691996],"iteration":491,"passed_time":0.505392778,"remaining_time":0.4704672608},
{"learn":[0.08650264448],"iteration":492,"passed_time":0.5060955109,"remaining_time":0.4691392464},
{"learn":[0.08641575056],"iteration":493,"passed_time":0.5067885869,"remaining_time":0.4678048495},
{"learn":[0.08635421416],"iteration":494,"passed_time":0.5074962885,"remaining_time":0.4664864874},
{"learn":[0.08628888752],"iteration":495,"passed_time":0.5083102153,"remaining_time":0.465267818},
{"learn":[0.08621659242],"iteration":496,"passed_time":0.5090697671,"remaining_time":0.4640012163},
{"learn":[0.08615028855],"iteration":497,"passed_time":0.5098024421,"remaining_time":0.4627122567},
{"learn":[0.0860828826],"iteration":498,"passed_time":0.5105284755,"remaining_time":0.461419524},
{"learn":[0.08606216951],"iteration":499,"passed_time":0.511257965,"remaining_time":0.4601321685},
{"learn":[0.08599113367],"iteration":500,"passed_time":0.5119661474,"remaining_time":0.4588279444},
{"learn":[0.08591199423],"iteration":501,"passed_time":0.5127226839,"remaining_time":0.4575692478},
{"learn":[0.08587773092],"iteration":502,"passed_time":0.513434162,"remaining_time":0.4562725058},
{"learn":[0.08585491837],"iteration":503,"passed_time":0.5141428252,"remaining_time":0.4549755953},
{"learn":[0.08575663986],"iteration":504,"passed_time":0.5148528909,"remaining_time":0.4536822504},
{"learn":[0.08565869316],"iteration":505,"passed_time":0.5155545118,"remaining_time":0.4523838009},
{"learn":[0.08563911202],"iteration":506,"passed_time":0.5162473074,"remaining_time":0.4510799944},
{"learn":[0.08556346851],"iteration":507,"passed_time":0.5169417459,"remaining_time":0.449780023},
{"learn":[0.08552623584],"iteration":508,"passed_time":0.5176453102,"remaining_time":0.4484903375},
{"learn":[0.0854301753],"iteration":509,"passed_time":0.5183476224,"remaining_time":0.4472018703},
{"learn":[0.08542207942],"iteration":510,"passed_time":0.5190447155,"remaining_time":0.4459112135},
{"learn":[0.08535605285],"iteration":511,"passed_time":0.519744964,"remaining_time":0.4446255747},
{"learn":[0.08532641003],"iteration":512,"passed_time":0.5204884879,"remaining_time":0.4433790823},
{"learn":[0.08528051341],"iteration":513,"passed_time":0.5211981729,"remaining_time":0.4421058432},
{"learn":[0.08520884321],"iteration":514,"passed_time":0.521961341,"remaining_time":0.4408799676},
{"learn":[0.08520563938],"iteration":515,"passed_time":0.5226578831,"remaining_time":0.4395998474},
{"learn":[0.08513013027],"iteration":516,"passed_time":0.5236131685,"remaining_time":0.4385386885},
{"learn":[0.08506992716],"iteration":517,"passed_time":0.5244703318,"remaining_time":0.4373961068},
{"learn":[0.08499747462],"iteration":518,"passed_time":0.5252177825,"remaining_time":0.4361635149},
{"learn":[0.08492988279],"iteration":519,"passed_time":0.5259289801,"remaining_time":0.4349028105},
{"learn":[0.08487126519],"iteration":520,"passed_time":0.5266421612,"remaining_time":0.4336458487},
{"learn":[0.08479582606],"iteration":521,"passed_time":0.5274562779,"remaining_time":0.4324737298},
{"learn":[0.08471779537],"iteration":522,"passed_time":0.5281920082,"remaining_time":0.4312389819},
{"learn":[0.08462358431],"iteration":523,"passed_time":0.528915918,"remaining_time":0.4299965287},
{"learn":[0.08456094956],"iteration":524,"passed_time":0.529611839,"remaining_time":0.4287333935},
{"learn":[0.08452996152],"iteration":525,"passed_time":0.5303043742,"remaining_time":0.4274696856},
{"learn":[0.08450894647],"iteration":526,"passed_time":0.5309929324,"remaining_time":0.4262049533},
{"learn":[0.08445282171],"iteration":527,"passed_time":0.5317026875,"remaining_time":0.4249593449},
{"learn":[0.08438701251],"iteration":528,"passed_time":0.5325539242,"remaining_time":0.4238283593},
{"learn":[0.08431628559],"iteration":529,"passed_time":0.5333005835,"remaining_time":0.4226155567},
{"learn":[0.08425443608],"iteration":530,"passed_time":0.5340268774,"remaining_time":0.42138844},
{"learn":[0.08417873777],"iteration":531,"passed_time":0.5347629884,"remaining_time":0.4201709194},
{"learn":[0.08413708909],"iteration":532,"passed_time":0.5354928585,"remaining_time":0.4189503227},
{"learn":[0.08401715753],"iteration":533,"passed_time":0.5361881384,"remaining_time":0.4177046172},
{"learn":[0.08396322718],"iteration":534,"passed_time":0.536968827,"remaining_time":0.4165272209},
{"learn":[0.08390514043],"iteration":535,"passed_time":0.5377356744,"remaining_time":0.4153406142},
{"learn":[0.08380912508],"iteration":536,"passed_time":0.53845721,"remaining_time":0.414120722},
{"learn":[0.08377674372],"iteration":537,"passed_time":0.5391682073,"remaining_time":0.4128946123},
{"learn":[0.0837006536],"iteration":538,"passed_time":0.5398757486,"remaining_time":0.4116677786},
{"learn":[0.08363348924],"iteration":539,"passed_time":0.5405867659,"remaining_time":0.4104455074},
{"learn":[0.08354383471],"iteration":540,"passed_time":0.5413238686,"remaining_time":0.409244847},
{"learn":[0.08341390088],"iteration":541,"passed_time":0.5420462256,"remaining_time":0.4080347971},
{"learn":[0.08330957443],"iteration":542,"passed_time":0.5427580844,"remaining_time":0.4068186747},
{"learn":[0.08330427402],"iteration":543,"passed_time":0.5434356335,"remaining_time":0.4055788},
{"learn":[0.08325239161],"iteration":544,"passed_time":0.5441844265,"remaining_time":0.4043939316},
{"learn":[0.08316201178],"iteration":545,"passed_time":0.5448969064,"remaining_time":0.4031837915},
{"learn":[0.08310722862],"iteration":546,"passed_time":0.5456281389,"remaining_time":0.4019892869},
{"learn":[0.08307106356],"iteration":547,"passed_time":0.5463418609,"remaining_time":0.4007836279},
{"learn":[0.08301528778],"iteration":548,"passed_time":0.5470546413,"remaining_time":0.3995790731},
{"learn":[0.08293243788],"iteration":549,"passed_time":0.5477543789,"remaining_time":0.398366821},
{"learn":[0.08287494252],"iteration":550,"passed_time":0.54844457,"remaining_time":0.3971495162},
{"learn":[0.0828084729],"iteration":551,"passed_time":0.5491460006,"remaining_time":0.3959422251},
{"learn":[0.08272091111],"iteration":552,"passed_time":0.5498314535,"remaining_time":0.394725293},
{"learn":[0.08267513535],"iteration":553,"passed_time":0.550535118,"remaining_time":0.3935232973},
{"learn":[0.08262122143],"iteration":554,"passed_time":0.5512635957,"remaining_time":0.3923407573},
{"learn":[0.08257643014],"iteration":555,"passed_time":0.5519456626,"remaining_time":0.3911269623},
{"learn":[0.08246411868],"iteration":556,"passed_time":0.5526566599,"remaining_time":0.3899354889},
{"learn":[0.0824599952],"iteration":557,"passed_time":0.5533631738,"remaining_time":0.3887425881},
{"learn":[0.08238047405],"iteration":558,"passed_time":0.5543372189,"remaining_time":0.3877385556},
{"learn":[0.08234417863],"iteration":559,"passed_time":0.5550703246,"remaining_time":0.3865668332},
{"learn":[0.08229973636],"iteration":560,"passed_time":0.555783105,"remaining_time":0.3853825808},
{"learn":[0.08228380166],"iteration":561,"passed_time":0.5566593153,"remaining_time":0.3843128369},
{"learn":[0.08226316735],"iteration":562,"passed_time":0.5573439567,"remaining_time":0.3831120981},
{"learn":[0.08217773454],"iteration":563,"passed_time":0.5580562763,"remaining_time":0.3819321323},
{"learn":[0.08214556817],"iteration":564,"passed_time":0.5587329739,"remaining_time":0.3807295486},
{"learn":[0.0820942722],"iteration":565,"passed_time":0.5594501519,"remaining_time":0.3795562868},
{"learn":[0.08201360286],"iteration":566,"passed_time":0.5601522236,"remaining_time":0.3783744297},
{"learn":[0.08196081406],"iteration":567,"passed_time":0.5608556778,"remaining_time":0.3771951918},
{"learn":[0.08188893528],"iteration":568,"passed_time":0.561559162,"remaining_time":0.3760176463},
{"learn":[0.08186424432],"iteration":569,"passed_time":0.5622535604,"remaining_time":0.3748357069},
{"learn":[0.08185450022],"iteration":570,"passed_time":0.5629243377,"remaining_time":0.3736397968},
{"learn":[0.08178380449],"iteration":571,"passed_time":0.5636404839,"remaining_time":0.3724757044},
{"learn":[0.08173632116],"iteration":572,"passed_time":0.5643339407,"remaining_time":0.3712982472},
{"learn":[0.0816420268],"iteration":573,"passed_time":0.5651302564,"remaining_time":0.3701898544},
{"learn":[0.08159542181],"iteration":574,"passed_time":0.5658409632,"remaining_time":0.3690267151},
{"learn":[0.08149332502],"iteration":575,"passed_time":0.5665729069,"remaining_time":0.3678789361},
{"learn":[0.08140047754],"iteration":576,"passed_time":0.5672811193,"remaining_time":0.3667172574},
{"learn":[0.08133854265],"iteration":577,"passed_time":0.5680108292,"remaining_time":0.3655709835},
{"learn":[0.08130235536],"iteration":578,"passed_time":0.5687262942,"remaining_time":0.364417021},
{"learn":[0.08127312787],"iteration":579,"passed_time":0.5694352279,"remaining_time":0.363260404},
{"learn":[0.08118498754],"iteration":580,"passed_time":0.5701592879,"remaining_time":0.362114935},
{"learn":[0.08111355675],"iteration":581,"passed_time":0.5708611293,"remaining_time":0.3609568652},
{"learn":[0.0810803565],"iteration":582,"passed_time":0.5715230311,"remaining_time":0.3597752185},
{"learn":[0.08101375151],"iteration":583,"passed_time":0.5722280079,"remaining_time":0.3586223474},
{"learn":[0.08094889906],"iteration":584,"passed_time":0.5729510762,"remaining_time":0.3574822954},
{"learn":[0.08094459653],"iteration":585,"passed_time":0.5736173857,"remaining_time":0.3563084102},
{"learn":[0.08088181829],"iteration":586,"passed_time":0.5743248568,"remaining_time":0.3551617087},
{"learn":[0.08086833941],"iteration":587,"passed_time":0.5749954939,"remaining_time":0.3539938245},
{"learn":[0.08085264868],"iteration":588,"passed_time":0.5756687455,"remaining_time":0.3528292311},
{"learn":[0.0807711175],"iteration":589,"passed_time":0.5763819967,"remaining_time":0.3516907098},
{"learn":[0.08069967604],"iteration":590,"passed_time":0.5771374212,"remaining_time":0.3505792457},
{"learn":[0.08060104453],"iteration":591,"passed_time":0.5778444015,"remaining_time":0.3494396888},
{"learn":[0.08054002078],"iteration":592,"passed_time":0.5785395312,"remaining_time":0.3482944564},
{"learn":[0.08049190163],"iteration":593,"passed_time":0.5792447985,"remaining_time":0.3471568153},
{"learn":[0.08045133632],"iteration":594,"passed_time":0.5799468502,"remaining_time":0.3460187089},
{"learn":[0.08043199187],"iteration":595,"passed_time":0.5806262725,"remaining_time":0.344868625},
{"learn":[0.08040304645],"iteration":596,"passed_time":0.581320721,"remaining_time":0.3437290025},
{"learn":[0.08032021828],"iteration":597,"passed_time":0.5820650908,"remaining_time":0.3426202541},
{"learn":[0.08031070464],"iteration":598,"passed_time":0.5829227086,"remaining_time":0.341579083},
{"learn":[0.08024687205],"iteration":599,"passed_time":0.583751571,"remaining_time":0.3405217497},
{"learn":[0.0801923894],"iteration":600,"passed_time":0.584514729,"remaining_time":0.3394270223},
{"learn":[0.08014540056],"iteration":601,"passed_time":0.5852820743,"remaining_time":0.3383358171},
{"learn":[0.0800679637],"iteration":602,"passed_time":0.5860499205,"remaining_time":0.3372459742},
{"learn":[0.07999284358],"iteration":603,"passed_time":0.5868122768,"remaining_time":0.3361540526},
{"learn":[0.07995823349],"iteration":604,"passed_time":0.5875337823,"remaining_time":0.3350399255},
{"learn":[0.07993925515],"iteration":605,"passed_time":0.5882731995,"remaining_time":0.3339372618},
{"learn":[0.07987801165],"iteration":606,"passed_time":0.589022233,"remaining_time":0.3328412288},
{"learn":[0.07979532462],"iteration":607,"passed_time":0.5898049851,"remaining_time":0.3317653041},
{"learn":[0.07973896872],"iteration":608,"passed_time":0.5905303374,"remaining_time":0.330658202},
{"learn":[0.07971712657],"iteration":609,"passed_time":0.5912792606,"remaining_time":0.3295654895},
{"learn":[0.0797014421],"iteration":610,"passed_time":0.5919935837,"remaining_time":0.3284547052},
{"learn":[0.07969561386],"iteration":611,"passed_time":0.5926788562,"remaining_time":0.3273291722},
{"learn":[0.0796171527],"iteration":612,"passed_time":0.5934739899,"remaining_time":0.3262654724},
{"learn":[0.07956156069],"iteration":613,"passed_time":0.5941839954,"remaining_time":0.3251560627},
{"learn":[0.07952645578],"iteration":614,"passed_time":0.5949143464,"remaining_time":0.3240590342},
{"learn":[0.07947164241],"iteration":615,"passed_time":0.595639889,"remaining_time":0.3229605892},
{"learn":[0.07938789263],"iteration":616,"passed_time":0.5963905152,"remaining_time":0.3218768907},
{"learn":[0.07931632049],"iteration":617,"passed_time":0.5971167991,"remaining_time":0.320781193},
{"learn":[0.07924561951],"iteration":618,"passed_time":0.5978210647,"remaining_time":0.319674915},
{"learn":[0.07923890624],"iteration":619,"passed_time":0.5985544108,"remaining_time":0.3185854122},
{"learn":[0.07911747715],"iteration":620,"passed_time":0.59934121,"remaining_time":0.3175253754},
{"learn":[0.07904314421],"iteration":621,"passed_time":0.6000842931,"remaining_time":0.3164431642},
{"learn":[0.07900967887],"iteration":622,"passed_time":0.6008416507,"remaining_time":0.3153695341},
{"learn":[0.07892024743],"iteration":623,"passed_time":0.6015973557,"remaining_time":0.3142960544},
{"learn":[0.07882401097],"iteration":624,"passed_time":0.602319813,"remaining_time":0.3132063027},
{"learn":[0.07878711418],"iteration":625,"passed_time":0.6030598107,"remaining_time":0.312126803},
{"learn":[0.07872822665],"iteration":626,"passed_time":0.6037767383,"remaining_time":0.3110365015},
{"learn":[0.07866962981],"iteration":627,"passed_time":0.6045360797,"remaining_time":0.3099691364},
{"learn":[0.07860796206],"iteration":628,"passed_time":0.6052526166,"remaining_time":0.3088809061},
{"learn":[0.07855959804],"iteration":629,"passed_time":0.6059718482,"remaining_time":0.3077952245},
{"learn":[0.07851065527],"iteration":630,"passed_time":0.6068109785,"remaining_time":0.3067713188},
{"learn":[0.07845443516],"iteration":631,"passed_time":0.6075719327,"remaining_time":0.3057086623},
{"learn":[0.07841356531],"iteration":632,"passed_time":0.608291555,"remaining_time":0.3046262605},
{"learn":[0.0783183977],"iteration":633,"passed_time":0.609001821,"remaining_time":0.3035403398},
{"learn":[0.07831384373],"iteration":634,"passed_time":0.6096791497,"remaining_time":0.3024392632},
{"learn":[0.07823916195],"iteration":635,"passed_time":0.6104234749,"remaining_time":0.3013725961},
{"learn":[0.07823666352],"iteration":636,"passed_time":0.6110967566,"remaining_time":0.3002720327},
{"learn":[0.07822881228],"iteration":637,"passed_time":0.6117829106,"remaining_time":0.2991791036},
{"learn":[0.078162748],"iteration":638,"passed_time":0.6125828731,"remaining_time":0.2981428381},
{"learn":[0.07810334386],"iteration":639,"passed_time":0.6133652446,"remaining_time":0.2970987904},
{"learn":[0.07805666476],"iteration":640,"passed_time":0.6142071096,"remaining_time":0.2960842385},
{"learn":[0.07802507494],"iteration":641,"passed_time":0.6149392337,"remaining_time":0.2950175763},
{"learn":[0.07795715659],"iteration":642,"passed_time":0.6157225167,"remaining_time":0.2939763805},
{"learn":[0.07793878463],"iteration":643,"passed_time":0.6164327928,"remaining_time":0.2929012959},
{"learn":[0.07787488376],"iteration":644,"passed_time":0.6171247269,"remaining_time":0.2918186693},
{"learn":[0.07781391877],"iteration":645,"passed_time":0.6178451706,"remaining_time":0.2907506685},
{"learn":[0.07775764918],"iteration":646,"passed_time":0.6185857894,"remaining_time":0.2896931904},
{"learn":[0.0776856661],"iteration":647,"passed_time":0.6193119931,"remaining_time":0.2886299721},
{"learn":[0.07763772885],"iteration":648,"passed_time":0.6200134138,"remaining_time":0.2875562982},
{"learn":[0.07760556726],"iteration":649,"passed_time":0.6208914016,"remaining_time":0.2865652623},
{"learn":[0.07757053404],"iteration":650,"passed_time":0.6216711586,"remaining_time":0.2855294568},
{"learn":[0.07751587314],"iteration":651,"passed_time":0.6223964607,"remaining_time":0.284469548},
{"learn":[0.07751025799],"iteration":652,"passed_time":0.623182749,"remaining_time":0.2834384019},
{"learn":[0.07748990499],"iteration":653,"passed_time":0.6239209436,"remaining_time":0.2823862375},
{"learn":[0.07743729418],"iteration":654,"passed_time":0.624652687,"remaining_time":0.2813321262},
{"learn":[0.07738325078],"iteration":655,"passed_time":0.625365828,"remaining_time":0.2802706607},
{"learn":[0.07737191378],"iteration":656,"passed_time":0.6260531741,"remaining_time":0.2791987519},
{"learn":[0.07733346015],"iteration":657,"passed_time":0.6267717746,"remaining_time":0.2781418818},
{"learn":[0.07728114342],"iteration":658,"passed_time":0.6274944923,"remaining_time":0.2770878562},
{"learn":[0.07722490263],"iteration":659,"passed_time":0.6282832144,"remaining_time":0.2760638366},
{"learn":[0.07721196864],"iteration":660,"passed_time":0.6289781738,"remaining_time":0.2749995344},
{"learn":[0.07715160382],"iteration":661,"passed_time":0.629692607,"remaining_time":0.27394482},
{"learn":[0.07707495326],"iteration":662,"passed_time":0.6304252019,"remaining_time":0.2728989939},
{"learn":[0.07697788915],"iteration":663,"passed_time":0.6311431012,"remaining_time":0.2718477815},
{"learn":[0.0769118324],"iteration":664,"passed_time":0.6319765916,"remaining_time":0.2708471107},
{"learn":[0.07682590674],"iteration":665,"passed_time":0.6327307044,"remaining_time":0.2698130931},
{"learn":[0.07680909511],"iteration":666,"passed_time":0.6334588711,"remaining_time":0.2687689063},
{"learn":[0.07675569521],"iteration":667,"passed_time":0.634163888,"remaining_time":0.2677158928},
{"learn":[0.07666783755],"iteration":668,"passed_time":0.6349175194,"remaining_time":0.2666843392},
{"learn":[0.07664829797],"iteration":669,"passed_time":0.6355989653,"remaining_time":0.2656234482},
{"learn":[0.0765567809],"iteration":670,"passed_time":0.6363305283,"remaining_time":0.2645845267},
{"learn":[0.07650831862],"iteration":671,"passed_time":0.6370225326,"remaining_time":0.2635301548},
{"learn":[0.07647689065],"iteration":672,"passed_time":0.6377394301,"remaining_time":0.2624871057},
{"learn":[0.07637993264],"iteration":673,"passed_time":0.6384630393,"remaining_time":0.2614477728},
{"learn":[0.07632545577],"iteration":674,"passed_time":0.6393143207,"remaining_time":0.2604613899},
{"learn":[0.0762678148],"iteration":675,"passed_time":0.6400214312,"remaining_time":0.2594169706},
{"learn":[0.07620622962],"iteration":676,"passed_time":0.6407155992,"remaining_time":0.2583683288},
{"learn":[0.07611949235],"iteration":677,"passed_time":0.6414016331,"remaining_time":0.2573174693},
{"learn":[0.07607198563],"iteration":678,"passed_time":0.6421061491,"remaining_time":0.256275061},
{"learn":[0.07598729627],"iteration":679,"passed_time":0.6428684256,"remaining_time":0.2552565807},
{"learn":[0.07592441615],"iteration":680,"passed_time":0.6436399286,"remaining_time":0.2542424975},
{"learn":[0.07585831535],"iteration":681,"passed_time":0.6443522582,"remaining_time":0.2532058727},
{"learn":[0.07580359158],"iteration":682,"passed_time":0.6450740743,"remaining_time":0.252173906},
{"learn":[0.07577271622],"iteration":683,"passed_time":0.6459357237,"remaining_time":0.2511972259},
{"learn":[0.0757692185],"iteration":684,"passed_time":0.6466158873,"remaining_time":0.2501506717},
{"learn":[0.07570649663],"iteration":685,"passed_time":0.6473514173,"remaining_time":0.249126493},
{"learn":[0.07570162247],"iteration":686,"passed_time":0.6480475988,"remaining_time":0.2480880909},
{"learn":[0.07569794396],"iteration":687,"passed_time":0.648720079,"remaining_time":0.247041658},
{"learn":[0.07561425672],"iteration":688,"passed_time":0.6494329195,"remaining_time":0.2460115994},
{"learn":[0.07558700841],"iteration":689,"passed_time":0.6501283196,"remaining_time":0.2449758886},
{"learn":[0.07552141873],"iteration":690,"passed_time":0.6508367124,"remaining_time":0.2439460326},
{"learn":[0.07545270874],"iteration":691,"passed_time":0.6515681352,"remaining_time":0.242925692},
{"learn":[0.07544924445],"iteration":692,"passed_time":0.6522360776,"remaining_time":0.2418826435},
{"learn":[0.07541192768],"iteration":693,"passed_time":0.6529349137,"remaining_time":0.2408520719},
{"learn":[0.07537911735],"iteration":694,"passed_time":0.6536406218,"remaining_time":0.2398249763},
{"learn":[0.07533379315],"iteration":695,"passed_time":0.6545180587,"remaining_time":0.2388614754},
{"learn":[0.07527975798],"iteration":696,"passed_time":0.655248039,"remaining_time":0.2378446971},
{"learn":[0.07523733903],"iteration":697,"passed_time":0.6560202624,"remaining_time":0.2368439916},
{"learn":[0.07512863745],"iteration":698,"passed_time":0.6567970241,"remaining_time":0.2358455695},
{"learn":[0.07506951888],"iteration":699,"passed_time":0.6575300096,"remaining_time":0.2348321463},
{"learn":[0.07502478054],"iteration":700,"passed_time":0.6582747757,"remaining_time":0.2338237078},
{"learn":[0.07497423334],"iteration":701,"passed_time":0.6590060683,"remaining_time":0.2328112606},
{"learn":[0.0749053267],"iteration":702,"passed_time":0.659709272,"remaining_time":0.2317897442},
{"learn":[0.07483863729],"iteration":703,"passed_time":0.6604152906,"remaining_time":0.2307701157},
{"learn":[0.07479269819],"iteration":704,"passed_time":0.6611517021,"remaining_time":0.229761939},
{"learn":[0.07476447889],"iteration":705,"passed_time":0.6618615273,"remaining_time":0.2287453437},
{"learn":[0.07471987092],"iteration":706,"passed_time":0.6625747986,"remaining_time":0.2277308006},
{"learn":[0.07471639627],"iteration":707,"passed_time":0.6632407274,"remaining_time":0.2267009266},
{"learn":[0.07469836523],"iteration":708,"passed_time":0.6639299969,"remaining_time":0.225680013},
{"learn":[0.07463389098],"iteration":709,"passed_time":0.6646432381,"remaining_time":0.2246681368},
{"learn":[0.07461159],"iteration":710,"passed_time":0.6657119578,"remaining_time":0.2237765934},
{"learn":[0.07455809527],"iteration":711,"passed_time":0.6664505932,"remaining_time":0.2227742151},
{"learn":[0.0745079205],"iteration":712,"passed_time":0.6671434189,"remaining_time":0.2217573496},
{"learn":[0.07445526609],"iteration":713,"passed_time":0.6678760638,"remaining_time":0.2207545533},
{"learn":[0.07438442215],"iteration":714,"passed_time":0.6685769735,"remaining_time":0.2197420822},
{"learn":[0.07433361163],"iteration":715,"passed_time":0.6692997112,"remaining_time":0.2187376151},
{"learn":[0.07429579625],"iteration":716,"passed_time":0.670008665,"remaining_time":0.2177294546},
{"learn":[0.07428343994],"iteration":717,"passed_time":0.6706840503,"remaining_time":0.2167112809},
{"learn":[0.0742740047],"iteration":718,"passed_time":0.6714040332,"remaining_time":0.215708389},
{"learn":[0.07422985534],"iteration":719,"passed_time":0.6721411158,"remaining_time":0.2147117453},
{"learn":[0.07417441443],"iteration":720,"passed_time":0.672827911,"remaining_time":0.2136998497},
{"learn":[0.07413258918],"iteration":721,"passed_time":0.6735397998,"remaining_time":0.2126967789},
{"learn":[0.0740435984],"iteration":722,"passed_time":0.6742693594,"remaining_time":0.2117000617},
{"learn":[0.07399707471],"iteration":723,"passed_time":0.6749680352,"remaining_time":0.2106944419},
{"learn":[0.07393434174],"iteration":724,"passed_time":0.6756989472,"remaining_time":0.2096996733},
{"learn":[0.07389706323],"iteration":725,"passed_time":0.676628395,"remaining_time":0.2087668877},
{"learn":[0.07384629549],"iteration":726,"passed_time":0.67736106,"remaining_time":0.2077737502},
{"learn":[0.07379354556],"iteration":727,"passed_time":0.6781768597,"remaining_time":0.2068066797},
{"learn":[0.07376908219],"iteration":728,"passed_time":0.6789336466,"remaining_time":0.2058221343},
{"learn":[0.07371888617],"iteration":729,"passed_time":0.6796605315,"remaining_time":0.2048292013},
{"learn":[0.07365075969],"iteration":730,"passed_time":0.6803525758,"remaining_time":0.2038265583},
{"learn":[0.07360722727],"iteration":731,"passed_time":0.6810743719,"remaining_time":0.2028336244},
{"learn":[0.07357503813],"iteration":732,"passed_time":0.6817810016,"remaining_time":0.2018369404},
{"learn":[0.07352119254],"iteration":733,"passed_time":0.6824973782,"remaining_time":0.2008439151},
{"learn":[0.07349209425],"iteration":734,"passed_time":0.6832100885,"remaining_time":0.1998505701},
{"learn":[0.07344441022],"iteration":735,"passed_time":0.6839261846,"remaining_time":0.1988589722},
{"learn":[0.0733891359],"iteration":736,"passed_time":0.6846407181,"remaining_time":0.1978676702},
{"learn":[0.07336533794],"iteration":737,"passed_time":0.6853433107,"remaining_time":0.1968736882},
{"learn":[0.07328175693],"iteration":738,"passed_time":0.6861033533,"remaining_time":0.1958968979},
{"learn":[0.07322977468],"iteration":739,"passed_time":0.6868105239,"remaining_time":0.1949056892},
{"learn":[0.07322544811],"iteration":740,"passed_time":0.6875182555,"remaining_time":0.1939154054},
{"learn":[0.07318784],"iteration":741,"passed_time":0.6882540359,"remaining_time":0.1929337459},
{"learn":[0.07312375073],"iteration":742,"passed_time":0.6889804801,"remaining_time":0.1919501472},
{"learn":[0.07309569261],"iteration":743,"passed_time":0.6897052213,"remaining_time":0.1909667683},
{"learn":[0.07307315378],"iteration":744,"passed_time":0.6904302029,"remaining_time":0.1899841498},
{"learn":[0.07301796661],"iteration":745,"passed_time":0.6911597725,"remaining_time":0.1890034767},
{"learn":[0.0729630901],"iteration":746,"passed_time":0.691848511,"remaining_time":0.1880123798},
{"learn":[0.07291971142],"iteration":747,"passed_time":0.6925532274,"remaining_time":0.1870264063},
{"learn":[0.07289703396],"iteration":748,"passed_time":0.693235705,"remaining_time":0.1860352159},
{"learn":[0.07281592321],"iteration":749,"passed_time":0.6939670878,"remaining_time":0.1850578901},
{"learn":[0.07277799872],"iteration":750,"passed_time":0.6946773237,"remaining_time":0.1840756157},
{"learn":[0.07269615876],"iteration":751,"passed_time":0.6953903345,"remaining_time":0.1830947955},
{"learn":[0.07263738268],"iteration":752,"passed_time":0.696137084,"remaining_time":0.1821235133},
{"learn":[0.07258626988],"iteration":753,"passed_time":0.6968514572,"remaining_time":0.1811444106},
{"learn":[0.0725291196],"iteration":754,"passed_time":0.6975859353,"remaining_time":0.1801712018},
{"learn":[0.07252607464],"iteration":755,"passed_time":0.698297774,"remaining_time":0.179192815},
{"learn":[0.07250672746],"iteration":756,"passed_time":0.6990364495,"remaining_time":0.1782219746},
{"learn":[0.07245699023],"iteration":757,"passed_time":0.6997675417,"remaining_time":0.1772498259},
{"learn":[0.07239400766],"iteration":758,"passed_time":0.7166045745,"remaining_time":0.1803313224},
{"learn":[0.07231722333],"iteration":759,"passed_time":0.7174646412,"remaining_time":0.1793661603},
{"learn":[0.07228338108],"iteration":760,"passed_time":0.7181768806,"remaining_time":0.1783645604},
{"learn":[0.07225612131],"iteration":761,"passed_time":0.7188647376,"remaining_time":0.1773577043},
{"learn":[0.07225427082],"iteration":762,"passed_time":0.7196087193,"remaining_time":0.1763654397},
{"learn":[0.07218676517],"iteration":763,"passed_time":0.7203284918,"remaining_time":0.1753679313},
{"learn":[0.07217081312],"iteration":764,"passed_time":0.7210026751,"remaining_time":0.174360124},
{"learn":[0.0721488445],"iteration":765,"passed_time":0.7217126808,"remaining_time":0.1733617928},
{"learn":[0.07207583668],"iteration":766,"passed_time":0.7224369712,"remaining_time":0.1723676216},
{"learn":[0.07203362753],"iteration":767,"passed_time":0.7231194389,"remaining_time":0.171364242},
{"learn":[0.07197914143],"iteration":768,"passed_time":0.7238330807,"remaining_time":0.1703690346},
{"learn":[0.07192130363],"iteration":769,"passed_time":0.724560747,"remaining_time":0.169377837},
{"learn":[0.07187964515],"iteration":770,"passed_time":0.7252447173,"remaining_time":0.1683771782},
{"learn":[0.07184709372],"iteration":771,"passed_time":0.7261474881,"remaining_time":0.1674277887},
{"learn":[0.07180934139],"iteration":772,"passed_time":0.7268920437,"remaining_time":0.166442292},
{"learn":[0.07174636259],"iteration":773,"passed_time":0.7276118163,"remaining_time":0.1654517825},
{"learn":[0.07166650319],"iteration":774,"passed_time":0.7283335322,"remaining_time":0.1644624105},
{"learn":[0.07166456539],"iteration":775,"passed_time":0.7290140865,"remaining_time":0.1634644988},
{"learn":[0.07158414322],"iteration":776,"passed_time":0.7297343098,"remaining_time":0.1624762363},
{"learn":[0.0715298675],"iteration":777,"passed_time":0.730448703,"remaining_time":0.1614873739},
{"learn":[0.07150003215],"iteration":778,"passed_time":0.7312411115,"remaining_time":0.1605163416},
{"learn":[0.07148283086],"iteration":779,"passed_time":0.7321114862,"remaining_time":0.1595627598},
{"learn":[0.07148082706],"iteration":780,"passed_time":0.7328153711,"remaining_time":0.1585733645},
{"learn":[0.071431548],"iteration":781,"passed_time":0.7336021803,"remaining_time":0.1576025144},
{"learn":[0.07139879939],"iteration":782,"passed_time":0.7342856997,"remaining_time":0.1566101045},
{"learn":[0.0713734677],"iteration":783,"passed_time":0.73502717,"remaining_time":0.1556307528},
{"learn":[0.07134560933],"iteration":784,"passed_time":0.7357526625,"remaining_time":0.1546486488},
{"learn":[0.07128908473],"iteration":785,"passed_time":0.7364907469,"remaining_time":0.1536698251},
{"learn":[0.07125376465],"iteration":786,"passed_time":0.7372033971,"remaining_time":0.1526863453},
{"learn":[0.07123954321],"iteration":787,"passed_time":0.7378777807,"remaining_time":0.1516956859},
{"learn":[0.07121825894],"iteration":788,"passed_time":0.7385690937,"remaining_time":0.1507092827},
{"learn":[0.07121548117],"iteration":789,"passed_time":0.739238729,"remaining_time":0.1497192362},
{"learn":[0.07117631435],"iteration":790,"passed_time":0.739943285,"remaining_time":0.1487370194},
{"learn":[0.07113907418],"iteration":791,"passed_time":0.7406597619,"remaining_time":0.1477578818},
{"learn":[0.0711302766],"iteration":792,"passed_time":0.7413352173,"remaining_time":0.1467712851},
{"learn":[0.07108540987],"iteration":793,"passed_time":0.7420476571,"remaining_time":0.1457927387},
{"learn":[0.07102184933],"iteration":794,"passed_time":0.7427667584,"remaining_time":0.1448161605},
{"learn":[0.07096144253],"iteration":795,"passed_time":0.7434362335,"remaining_time":0.1438306281},
{"learn":[0.07090710479],"iteration":796,"passed_time":0.7441684577,"remaining_time":0.1428579348},
{"learn":[0.0708389866],"iteration":797,"passed_time":0.7449079445,"remaining_time":0.1418872275},
{"learn":[0.07077956406],"iteration":798,"passed_time":0.7456764218,"remaining_time":0.1409225778},
{"learn":[0.0707767802],"iteration":799,"passed_time":0.7463777122,"remaining_time":0.139945821},
{"learn":[0.07072394952],"iteration":800,"passed_time":0.7470829695,"remaining_time":0.13897049},
{"learn":[0.07067458305],"iteration":801,"passed_time":0.7477895491,"remaining_time":0.1379960764},
{"learn":[0.07063613064],"iteration":802,"passed_time":0.7484939749,"remaining_time":0.1370219356},
{"learn":[0.07058859451],"iteration":803,"passed_time":0.7491915088,"remaining_time":0.1360472143},
{"learn":[0.07055977433],"iteration":804,"passed_time":0.749890966,"remaining_time":0.135073528},
{"learn":[0.07053012991],"iteration":805,"passed_time":0.7505901928,"remaining_time":0.1341004811},
{"learn":[0.07048267489],"iteration":806,"passed_time":0.7512942279,"remaining_time":0.1331289648},
{"learn":[0.07045528065],"iteration":807,"passed_time":0.7519852605,"remaining_time":0.1321558255},
{"learn":[0.07039329488],"iteration":808,"passed_time":0.7527208305,"remaining_time":0.131191146},
{"learn":[0.070350164],"iteration":809,"passed_time":0.7534553187,"remaining_time":0.1302268452},
{"learn":[0.07031146538],"iteration":810,"passed_time":0.7541612772,"remaining_time":0.1292582214},
{"learn":[0.07028651459],"iteration":811,"passed_time":0.7548727052,"remaining_time":0.128291174},
{"learn":[0.07025704664],"iteration":812,"passed_time":0.7555924677,"remaining_time":0.12732616},
{"learn":[0.07019329347],"iteration":813,"passed_time":0.7563048073,"remaining_time":0.1263605084},
{"learn":[0.07019176136],"iteration":814,"passed_time":0.7569725393,"remaining_time":0.1253880893},
{"learn":[0.07018904469],"iteration":815,"passed_time":0.7576851799,"remaining_time":0.1244237918},
{"learn":[0.07015325819],"iteration":816,"passed_time":0.758384006,"remaining_time":0.1234578614},
{"learn":[0.07015057641],"iteration":817,"passed_time":0.7590779235,"remaining_time":0.1224917921},
{"learn":[0.07009068204],"iteration":818,"passed_time":0.759801683,"remaining_time":0.1215311605},
{"learn":[0.07002168014],"iteration":819,"passed_time":0.7606134456,"remaining_time":0.1205850585},
{"learn":[0.06998969222],"iteration":820,"passed_time":0.7613943846,"remaining_time":0.1196344405},
{"learn":[0.06998134348],"iteration":821,"passed_time":0.7620902356,"remaining_time":0.1186709856},
{"learn":[0.06996552444],"iteration":822,"passed_time":0.762774316,"remaining_time":0.1177063647},
{"learn":[0.06996079398],"iteration":823,"passed_time":0.7634670214,"remaining_time":0.1167437436},
{"learn":[0.06991270638],"iteration":824,"passed_time":0.7641962404,"remaining_time":0.1157873092},
{"learn":[0.06984694432],"iteration":825,"passed_time":0.7649197996,"remaining_time":0.1148305752},
{"learn":[0.0698034109],"iteration":826,"passed_time":0.7656393417,"remaining_time":0.1138738078},
{"learn":[0.06976052509],"iteration":827,"passed_time":0.7664294066,"remaining_time":0.1129280043},
{"learn":[0.06972918214],"iteration":828,"passed_time":0.7671505515,"remaining_time":0.1119725172},
{"learn":[0.06967763182],"iteration":829,"passed_time":0.7678446894,"remaining_time":0.11101369},
{"learn":[0.06960710297],"iteration":830,"passed_time":0.7686049324,"remaining_time":0.1100649663},
{"learn":[0.0695704661],"iteration":831,"passed_time":0.7693213191,"remaining_time":0.1091104755},
{"learn":[0.06951573036],"iteration":832,"passed_time":0.7700433856,"remaining_time":0.1081573543},
{"learn":[0.06947352807],"iteration":833,"passed_time":0.7707533611,"remaining_time":0.1072031054},
{"learn":[0.06943256537],"iteration":834,"passed_time":0.7714706994,"remaining_time":0.1062504556},
{"learn":[0.0693719079],"iteration":835,"passed_time":0.7722050173,"remaining_time":0.1053006842},
{"learn":[0.06931663968],"iteration":836,"passed_time":0.7729107354,"remaining_time":0.1043475664},
{"learn":[0.0692786861],"iteration":837,"passed_time":0.773609872,"remaining_time":0.1033941595},
{"learn":[0.06921647523],"iteration":838,"passed_time":0.7743326698,"remaining_time":0.1024444891},
{"learn":[0.06914498154],"iteration":839,"passed_time":0.7750593544,"remaining_time":0.1014958678},
{"learn":[0.06910613826],"iteration":840,"passed_time":0.7758150995,"remaining_time":0.1005515408},
{"learn":[0.06907197316],"iteration":841,"passed_time":0.7765552475,"remaining_time":0.0996056612},
{"learn":[0.06901966655],"iteration":842,"passed_time":0.7773413751,"remaining_time":0.09866610574},
{"learn":[0.06900667235],"iteration":843,"passed_time":0.7780502387,"remaining_time":0.09771721007},
{"learn":[0.06894898803],"iteration":844,"passed_time":0.7787981302,"remaining_time":0.09677373215},
{"learn":[0.06888446473],"iteration":845,"passed_time":0.7795281906,"remaining_time":0.09582852462},
{"learn":[0.06883456857],"iteration":846,"passed_time":0.7802304928,"remaining_time":0.09488044953},
{"learn":[0.06883279624],"iteration":847,"passed_time":0.7809060383,"remaining_time":0.09392973574},
{"learn":[0.06876800258],"iteration":848,"passed_time":0.7816278444,"remaining_time":0.09298517348},
{"learn":[0.06874906253],"iteration":849,"passed_time":0.7823321801,"remaining_time":0.09203908001},
{"learn":[0.0686853397],"iteration":850,"passed_time":0.7830341216,"remaining_time":0.09109327619},
{"learn":[0.06864638921],"iteration":851,"passed_time":0.7837596642,"remaining_time":0.0901507595},
{"learn":[0.0685951651],"iteration":852,"passed_time":0.7844800879,"remaining_time":0.08920816943},
{"learn":[0.06857528485],"iteration":853,"passed_time":0.7851672036,"remaining_time":0.08826235544},
{"learn":[0.0685360334],"iteration":854,"passed_time":0.7858714592,"remaining_time":0.08731905102},
{"learn":[0.06849737263],"iteration":855,"passed_time":0.7865986146,"remaining_time":0.08637881982},
{"learn":[0.06842363118],"iteration":856,"passed_time":0.7873333331,"remaining_time":0.08543990663},
{"learn":[0.06842189599],"iteration":857,"passed_time":0.7881315622,"remaining_time":0.0845082794},
{"learn":[0.06837053742],"iteration":858,"passed_time":0.788863005,"remaining_time":0.08356988761},
{"learn":[0.06836869346],"iteration":859,"passed_time":0.7895342431,"remaining_time":0.08262567661},
{"learn":[0.06834769257],"iteration":860,"passed_time":0.7902375971,"remaining_time":0.08168541945},
{"learn":[0.06829233467],"iteration":861,"passed_time":0.790992351,"remaining_time":0.08075095926},
{"learn":[0.06825916255],"iteration":862,"passed_time":0.7917278609,"remaining_time":0.07981497555},
{"learn":[0.06818723286],"iteration":863,"passed_time":0.7924535036,"remaining_time":0.07887847374},
{"learn":[0.06818565294],"iteration":864,"passed_time":0.7931340279,"remaining_time":0.07793802586},
{"learn":[0.06816196965],"iteration":865,"passed_time":0.7938523579,"remaining_time":0.07700184534},
{"learn":[0.06811576414],"iteration":866,"passed_time":0.7945675325,"remaining_time":0.07606586528},
{"learn":[0.06806740685],"iteration":867,"passed_time":0.7952852915,"remaining_time":0.07513063814},
{"learn":[0.0680217242],"iteration":868,"passed_time":0.7959904687,"remaining_time":0.07419473874},
{"learn":[0.06799178068],"iteration":869,"passed_time":0.7966967077,"remaining_time":0.07325946737},
{"learn":[0.0679483322],"iteration":870,"passed_time":0.7974051605,"remaining_time":0.07232492271},
{"learn":[0.06790572316],"iteration":871,"passed_time":0.7981284892,"remaining_time":0.07139222725},
{"learn":[0.06790406013],"iteration":872,"passed_time":0.7988913768,"remaining_time":0.07046350059},
{"learn":[0.06785616335],"iteration":873,"passed_time":0.7996387474,"remaining_time":0.06953380412},
{"learn":[0.06780799845],"iteration":874,"passed_time":0.8003677059,"remaining_time":0.06860294622},
{"learn":[0.06778276996],"iteration":875,"passed_time":0.8011250639,"remaining_time":0.06767494832},
{"learn":[0.06774124794],"iteration":876,"passed_time":0.8018506465,"remaining_time":0.06674469464},
{"learn":[0.06770991187],"iteration":877,"passed_time":0.8025673537,"remaining_time":0.06581417935},
{"learn":[0.06769865119],"iteration":878,"passed_time":0.8032453236,"remaining_time":0.06488102158},
{"learn":[0.06766815506],"iteration":879,"passed_time":0.8039517028,"remaining_time":0.06395070363},
{"learn":[0.06763256367],"iteration":880,"passed_time":0.8046585228,"remaining_time":0.06302092857},
{"learn":[0.06758376318],"iteration":881,"passed_time":0.8054462336,"remaining_time":0.06209789556},
{"learn":[0.06752908168],"iteration":882,"passed_time":0.8061840375,"remaining_time":0.06117138223},
{"learn":[0.06749050183],"iteration":883,"passed_time":0.8068955156,"remaining_time":0.06024333035},
{"learn":[0.06743778304],"iteration":884,"passed_time":0.8076205874,"remaining_time":0.0593167663},
{"learn":[0.0673919782],"iteration":885,"passed_time":0.8083226291,"remaining_time":0.05838899352},
{"learn":[0.06739054199],"iteration":886,"passed_time":0.808996652,"remaining_time":0.05745973966},
{"learn":[0.06734027298],"iteration":887,"passed_time":0.8097098731,"remaining_time":0.05653379745},
{"learn":[0.0672999368],"iteration":888,"passed_time":0.8104312785,"remaining_time":0.05560889538},
{"learn":[0.06723715514],"iteration":889,"passed_time":0.8112296278,"remaining_time":0.05468963783},
{"learn":[0.06721633384],"iteration":890,"passed_time":0.8119636952,"remaining_time":0.05376639508},
{"learn":[0.06718279442],"iteration":891,"passed_time":0.8126861124,"remaining_time":0.05284281897},
{"learn":[0.06713801396],"iteration":892,"passed_time":0.8134197891,"remaining_time":0.05192041207},
{"learn":[0.06709337533],"iteration":893,"passed_time":0.8141454018,"remaining_time":0.05099792226},
{"learn":[0.06708228698],"iteration":894,"passed_time":0.8148486456,"remaining_time":0.05007449778},
{"learn":[0.06705559896],"iteration":895,"passed_time":0.8155534121,"remaining_time":0.04915165653},
{"learn":[0.06704405708],"iteration":896,"passed_time":0.816241239,"remaining_time":0.04822830063},
{"learn":[0.06700766817],"iteration":897,"passed_time":0.8169392136,"remaining_time":0.04730605691},
{"learn":[0.06697146465],"iteration":898,"passed_time":0.8176493194,"remaining_time":0.04638500032},
{"learn":[0.06692393699],"iteration":899,"passed_time":0.8183905192,"remaining_time":0.04546613996},
{"learn":[0.06692162134],"iteration":900,"passed_time":0.8190596436,"remaining_time":0.0445437542},
{"learn":[0.06688508148],"iteration":901,"passed_time":0.8197714323,"remaining_time":0.04362420039},
{"learn":[0.0668835255],"iteration":902,"passed_time":0.8205328769,"remaining_time":0.04270769127},
{"learn":[0.06684526282],"iteration":903,"passed_time":0.82127024,"remaining_time":0.04179029983},
{"learn":[0.06683873865],"iteration":904,"passed_time":0.8219875884,"remaining_time":0.04087231102},
{"learn":[0.06678626061],"iteration":905,"passed_time":0.8227048465,"remaining_time":0.03995476076},
{"learn":[0.06675716979],"iteration":906,"passed_time":0.8234258412,"remaining_time":0.0390378293},
{"learn":[0.06674095882],"iteration":907,"passed_time":0.824157815,"remaining_time":0.03812183726},
{"learn":[0.06669236161],"iteration":908,"passed_time":0.824901399,"remaining_time":0.03720677377},
{"learn":[0.06666101355],"iteration":909,"passed_time":0.8256237961,"remaining_time":0.03629115587},
{"learn":[0.06660364265],"iteration":910,"passed_time":0.8263606684,"remaining_time":0.03537658185},
{"learn":[0.06654804998],"iteration":911,"passed_time":0.8270951265,"remaining_time":0.03446229694},
{"learn":[0.0665105399],"iteration":912,"passed_time":0.8278351543,"remaining_time":0.03354863166},
{"learn":[0.06645123909],"iteration":913,"passed_time":0.8285648641,"remaining_time":0.03263493994},
{"learn":[0.06636914521],"iteration":914,"passed_time":0.8293062042,"remaining_time":0.03172209524},
{"learn":[0.06634316024],"iteration":915,"passed_time":0.8300275695,"remaining_time":0.03080888359},
{"learn":[0.06629617927],"iteration":916,"passed_time":0.830738126,"remaining_time":0.02989570137},
{"learn":[0.0662566706],"iteration":917,"passed_time":0.8314394164,"remaining_time":0.02898263761},
{"learn":[0.06625464262],"iteration":918,"passed_time":0.8321111955,"remaining_time":0.02806903924},
{"learn":[0.06625271502],"iteration":919,"passed_time":0.8328225033,"remaining_time":0.02715725554},
{"learn":[0.06622366749],"iteration":920,"passed_time":0.8335666482,"remaining_time":0.02624694115},
{"learn":[0.06617739227],"iteration":921,"passed_time":0.8344006496,"remaining_time":0.02533971604},
{"learn":[0.0661520025],"iteration":922,"passed_time":0.8351244191,"remaining_time":0.02442942504},
{"learn":[0.06609005805],"iteration":923,"passed_time":0.8359721547,"remaining_time":0.023523026},
{"learn":[0.06600850143],"iteration":924,"passed_time":0.8367138654,"remaining_time":0.02261388826},
{"learn":[0.06598352866],"iteration":925,"passed_time":0.8374090953,"remaining_time":0.02170390744},
{"learn":[0.06597479403],"iteration":926,"passed_time":0.8380951892,"remaining_time":0.02079416327},
{"learn":[0.06593728488],"iteration":927,"passed_time":0.8388256403,"remaining_time":0.01988595268},
{"learn":[0.06590107316],"iteration":928,"passed_time":0.8395488789,"remaining_time":0.01897796174},
{"learn":[0.06583906236],"iteration":929,"passed_time":0.8402492177,"remaining_time":0.01806987565},
{"learn":[0.06580106143],"iteration":930,"passed_time":0.8409589227,"remaining_time":0.01716242699},
{"learn":[0.06573815179],"iteration":931,"passed_time":0.8416700101,"remaining_time":0.01625542938},
{"learn":[0.06573694859],"iteration":932,"passed_time":0.8423390844,"remaining_time":0.01534808621},
{"learn":[0.06569546831],"iteration":933,"passed_time":0.8430416871,"remaining_time":0.01444182762},
{"learn":[0.06569390563],"iteration":934,"passed_time":0.8437081469,"remaining_time":0.01353542482},
{"learn":[0.06565810254],"iteration":935,"passed_time":0.844446662,"remaining_time":0.01263061247},
{"learn":[0.06564459227],"iteration":936,"passed_time":0.8451861789,"remaining_time":0.01172616897},
{"learn":[0.0656178887],"iteration":937,"passed_time":0.8458975569,"remaining_time":0.01082171715},
{"learn":[0.06561166301],"iteration":938,"passed_time":0.8466346195,"remaining_time":0.009917977438},
{"learn":[0.06557484109],"iteration":939,"passed_time":0.8473441943,"remaining_time":0.00901429994},
{"learn":[0.06551180555],"iteration":940,"passed_time":0.8480926969,"remaining_time":0.008111407303},
{"learn":[0.0654737514],"iteration":941,"passed_time":0.8487966318,"remaining_time":0.007208463965},
{"learn":[0.06545385774],"iteration":942,"passed_time":0.8494664575,"remaining_time":0.006305689504},
{"learn":[0.06540262003],"iteration":943,"passed_time":0.8501624486,"remaining_time":0.005403574885},
{"learn":[0.06534886732],"iteration":944,"passed_time":0.850952774,"remaining_time":0.004502395629},
{"learn":[0.06530550449],"iteration":945,"passed_time":0.8517058645,"remaining_time":0.003601293296},
{"learn":[0.06527943062],"iteration":946,"passed_time":0.8524328897,"remaining_time":0.002700420981},
{"learn":[0.06525527362],"iteration":947,"passed_time":0.853146772,"remaining_time":0.001799887705},
{"learn":[0.06520303607],"iteration":948,"passed_time":0.8538728354,"remaining_time":0.0008997606274},
{"learn":[0.0651602546],"iteration":949,"passed_time":0.8545954529,"remaining_time":0}
]}